Workbook

Sheet data
C1: mobility, reliability, and connectvity | AE1: safety and security - Ardurra | AI1: asset preservation and technology deployment | AP1: economic competitiveness, cross-border resiliency, and sustainable funding - these measures are either addressed in equity (for econ comp) or not measurable, ignore | AQ1: customer service, stewardship and sustainability, and equity
A2: corridor_j | B2: Miles | C2: existing vc | D2: forecasted vc | E2: Congestion_metric | F2: forecasted LOS | G2: TTRI | H2: delay_psgr_s_corr | I2: delay_trk_s_corr | J2: PV_FB_22 | K2: PV_SB_22 | L2: Trk_FB_22 | M2: Trk_SB_22 | N2: PV_Fcat_22 | O2: PV_Scat_22 | P2: Trk_Fcat_22 | Q2: Trk_Scat_22 | R2: PV_Inefficiency_22 | S2: Trk_Inefficiency_22 | T2: PV_FB_50 | U2: PV_SB_50 | V2: Trk_FB_50 | W2: Trk_SB_50 | X2: PV_Fcat_50 | Y2: PV_Scat_50 | Z2: Trk_Fcat_50 | AA2: Trk_Scat_50 | AB2: PV_Inefficiency_50 | AC2: Trk_Inefficiency_50 | AD2: Multimodal | AE2: Safety | AF2: truck-related crashes | AG2: bridge strikes - Not Important bc addressed in 15 ft or lower metric | AH2: RR_crash | AI2: frontage roads | AJ2: % lane mileage with 2 or less lanes | AK2: shoulder width | AL2: Pavement Conditions | AM2: Bridge Condition | AN2: 16' bridge or lower | AO2: ITS-Ardurra | AP2: exposure to risk | AQ2: access to historic, cultural, and tourist activities | AR2: EV charging inventory and proximity | AS2: access to rest areas/truck parking | AT2: R2R_N_corridors_Final_Equity_091124
A3: 240AA1005 | B3: 12.562325 | C3: 0 | D3: 0 | E3: 1 | G3: 0 | H3: 0 | I3: 0 | J3: No_Change | K3: No_Change | L3: No_Change | M3: No_Change | N3: =IF(OR(J3="Utilize_High",J3="Utilize_Med",J3="Utilize_Low"),"Low",IF(J3="No_Change","Med","High")) -> Med | O3: =IF(OR(K3="Utilize_High",K3="Utilize_Med",K3="Utilize_Low"),"Low",IF(K3="No_Change","Med","High")) -> Med | P3: =IF(OR(L3="Utilize_High",L3="Utilize_Med",L3="Utilize_Low"),"Low",IF(L3="No_Change","Med","High")) -> Med | Q3: =IF(OR(M3="Utilize_High",M3="Utilize_Med",M3="Utilize_Low"),"Low",IF(M3="No_Change","Med","High")) -> Med | R3: =IF(N3=O3,N3,IF(OR(N3="High",O3="High"),"High",IF(OR(N3="Med",O3="Med"),"Med","Low"))) -> Med | S3: =IF(P3=Q3,P3,IF(OR(P3="High",Q3="High"),"High",IF(OR(P3="Med",Q3="Med"),"Med","Low"))) -> Med | T3: =VLOOKUP(A3,[1]R2R_N_corridors_Final50!$A$2:$AM$57,39,FALSE) -> No_Change | U3: =VLOOKUP(A3,[1]R2R_N_corridors_Final50!$A$2:$AO$57,41,FALSE) -> No_Change | V3: =VLOOKUP(A3,[1]R2R_N_corridors_Final50!$A$2:$AN$57,40,FALSE) -> No_Change | W3: =VLOOKUP(A3,[1]R2R_N_corridors_Final50!$A$2:$AP$57,42,FALSE) -> No_Change | X3: =IF(OR(T3="Utilize_High",T3="Utilize_Med",T3="Utilize_Low"),"Low",IF(T3="No_Change","Med","High")) -> Med | Y3: =IF(OR(U3="Utilize_High",U3="Utilize_Med",U3="Utilize_Low"),"Low",IF(U3="No_Change","Med","High")) -> Med | Z3: =IF(OR(V3="Utilize_High",V3="Utilize_Med",V3="Utilize_Low"),"Low",IF(V3="No_Change","Med","High")) -> Med | AA3: =IF(OR(W3="Utilize_High",W3="Utilize_Med",W3="Utilize_Low"),"Low",IF(W3="No_Change","Med","High")) -> Med | AB3: =IF(X3=Y3,X3,IF(OR(X3="High",Y3="High"),"High",IF(OR(X3="Med",Y3="Med"),"Med","Low"))) -> Med | AC3: =IF(Z3=AA3,Z3,IF(OR(Z3="High",AA3="High"),"High",IF(OR(Z3="Med",AA3="Med"),"Med","Low"))) -> Med | AD3: =VLOOKUP(A3,MultimodalConnectivity_Corridor!$A$2:$K$57,11,FALSE) -> Low | AE3: =VLOOKUP(A3,[2]METRICS!$AA$2:$AC$70,3,FALSE) -> 0 | AG3: 0 | AH3: =VLOOKUP(A3,[2]METRICS!$AA$2:$AD$70,4,FALSE) -> 0 | AI3: 0 | AJ3: 100 | AK3: 0 | AL3: 1 | AM3: 2.5482162 | AN3: 0 | AO3: 1 | AQ3: 209 | AR3: 1.4 | AS3: 2 | AT3: Low
A4: FM0305-KG | B4: 19.554896 | C4: 0.089692533 | D4: 0.11675096 | E4: 1 | G4: 0 | H4: 0 | I4: 0 | J4: Avoid_Med | K4: Avoid_Med | L4: Avoid_High | M4: Avoid_High | N4: =IF(OR(J4="Utilize_High",J4="Utilize_Med",J4="Utilize_Low"),"Low",IF(J4="No_Change","Med","High")) -> High | O4: =IF(OR(K4="Utilize_High",K4="Utilize_Med",K4="Utilize_Low"),"Low",IF(K4="No_Change","Med","High")) -> High | P4: =IF(OR(L4="Utilize_High",L4="Utilize_Med",L4="Utilize_Low"),"Low",IF(L4="No_Change","Med","High")) -> High | Q4: =IF(OR(M4="Utilize_High",M4="Utilize_Med",M4="Utilize_Low"),"Low",IF(M4="No_Change","Med","High")) -> High | R4: =IF(N4=O4,N4,IF(OR(N4="High",O4="High"),"High",IF(OR(N4="Med",O4="Med"),"Med","Low"))) -> High | S4: =IF(P4=Q4,P4,IF(OR(P4="High",Q4="High"),"High",IF(OR(P4="Med",Q4="Med"),"Med","Low"))) -> High | T4: =VLOOKUP(A4,[1]R2R_N_corridors_Final50!$A$2:$AM$57,39,FALSE) -> Avoid_Low | U4: =VLOOKUP(A4,[1]R2R_N_corridors_Final50!$A$2:$AO$57,41,FALSE) -> Avoid_Low | V4: =VLOOKUP(A4,[1]R2R_N_corridors_Final50!$A$2:$AN$57,40,FALSE) -> Avoid_High | W4: =VLOOKUP(A4,[1]R2R_N_corridors_Final50!$A$2:$AP$57,42,FALSE) -> Avoid_High | X4: =IF(OR(T4="Utilize_High",T4="Utilize_Med",T4="Utilize_Low"),"Low",IF(T4="No_Change","Med","High")) -> High | Y4: =IF(OR(U4="Utilize_High",U4="Utilize_Med",U4="Utilize_Low"),"Low",IF(U4="No_Change","Med","High")) -> High | Z4: =IF(OR(V4="Utilize_High",V4="Utilize_Med",V4="Utilize_Low"),"Low",IF(V4="No_Change","Med","High")) -> High | AA4: =IF(OR(W4="Utilize_High",W4="Utilize_Med",W4="Utilize_Low"),"Low",IF(W4="No_Change","Med","High")) -> High | AB4: =IF(X4=Y4,X4,IF(OR(X4="High",Y4="High"),"High",IF(OR(X4="Med",Y4="Med"),"Med","Low"))) -> High | AC4: =IF(Z4=AA4,Z4,IF(OR(Z4="High",AA4="High"),"High",IF(OR(Z4="Med",AA4="Med"),"Med","Low"))) -> High | AD4: =VLOOKUP(A4,MultimodalConnectivity_Corridor!$A$2:$K$57,11,FALSE) -> Low | AE4: =VLOOKUP(A4,[2]METRICS!$AA$2:$AC$70,3,FALSE) -> 8479.4644 | AG4: 0 | AH4: =VLOOKUP(A4,[2]METRICS!$AA$2:$AD$70,4,FALSE) -> 0 | AI4: 0 | AJ4: 89.065645 | AK4: 6.605263 | AL4: 1.1051689 | AM4: 1.0008768 | AN4: 0 | AO4: 1.0499296 | AQ4: 101.45 | AR4: 0.2 | AS4: 2 | AT4: Medium
A5: FM0490-KG | B5: 13.986049 | C5: 0.045740773 | D5: 0.06815768 | E5: 1 | G5: 0 | H5: 0 | I5: 0 | J5: Utilize_High | K5: Utilize_High | L5: Utilize_Low | M5: Utilize_Low | N5: =IF(OR(J5="Utilize_High",J5="Utilize_Med",J5="Utilize_Low"),"Low",IF(J5="No_Change","Med","High")) -> Low | O5: =IF(OR(K5="Utilize_High",K5="Utilize_Med",K5="Utilize_Low"),"Low",IF(K5="No_Change","Med","High")) -> Low | P5: =IF(OR(L5="Utilize_High",L5="Utilize_Med",L5="Utilize_Low"),"Low",IF(L5="No_Change","Med","High")) -> Low | Q5: =IF(OR(M5="Utilize_High",M5="Utilize_Med",M5="Utilize_Low"),"Low",IF(M5="No_Change","Med","High")) -> Low | R5: =IF(N5=O5,N5,IF(OR(N5="High",O5="High"),"High",IF(OR(N5="Med",O5="Med"),"Med","Low"))) -> Low | S5: =IF(P5=Q5,P5,IF(OR(P5="High",Q5="High"),"High",IF(OR(P5="Med",Q5="Med"),"Med","Low"))) -> Low | T5: =VLOOKUP(A5,[1]R2R_N_corridors_Final50!$A$2:$AM$57,39,FALSE) -> Utilize_High | U5: =VLOOKUP(A5,[1]R2R_N_corridors_Final50!$A$2:$AO$57,41,FALSE) -> Utilize_High | V5: =VLOOKUP(A5,[1]R2R_N_corridors_Final50!$A$2:$AN$57,40,FALSE) -> Utilize_High | W5: =VLOOKUP(A5,[1]R2R_N_corridors_Final50!$A$2:$AP$57,42,FALSE) -> Utilize_High | X5: =IF(OR(T5="Utilize_High",T5="Utilize_Med",T5="Utilize_Low"),"Low",IF(T5="No_Change","Med","High")) -> Low | Y5: =IF(OR(U5="Utilize_High",U5="Utilize_Med",U5="Utilize_Low"),"Low",IF(U5="No_Change","Med","High")) -> Low | Z5: =IF(OR(V5="Utilize_High",V5="Utilize_Med",V5="Utilize_Low"),"Low",IF(V5="No_Change","Med","High")) -> Low | AA5: =IF(OR(W5="Utilize_High",W5="Utilize_Med",W5="Utilize_Low"),"Low",IF(W5="No_Change","Med","High")) -> Low | AB5: =IF(X5=Y5,X5,IF(OR(X5="High",Y5="High"),"High",IF(OR(X5="Med",Y5="Med"),"Med","Low"))) -> Low | AC5: =IF(Z5=AA5,Z5,IF(OR(Z5="High",AA5="High"),"High",IF(OR(Z5="Med",AA5="Med"),"Med","Low"))) -> Low | AD5: =VLOOKUP(A5,MultimodalConnectivity_Corridor!$A$2:$K$57,11,FALSE) -> Low | AE5: =VLOOKUP(A5,[2]METRICS!$AA$2:$AC$70,3,FALSE) -> 8375.8624 | AG5: 0 | AH5: =VLOOKUP(A5,[2]METRICS!$AA$2:$AD$70,4,FALSE) -> 0.010102 | AI5: 0 | AJ5: 100 | AK5: 3 | AL5: 1.0780987 | AM5: 1.0006469 | AN5: 0 | AO5: 1 | AQ5: 516.1 | AR5: 5.9 | AS5: 3 | AT5: Low
A6: FM0624-KG | B6: 97.643794 | C6: 0.046073154 | D6: 0.042790414 | E6: 1 | G6: 0 | H6: 0 | I6: 0 | J6: Utilize_Low | K6: Utilize_Low | L6: Avoid_Low | M6: Avoid_Low | N6: =IF(OR(J6="Utilize_High",J6="Utilize_Med",J6="Utilize_Low"),"Low",IF(J6="No_Change","Med","High")) -> Low | O6: =IF(OR(K6="Utilize_High",K6="Utilize_Med",K6="Utilize_Low"),"Low",IF(K6="No_Change","Med","High")) -> Low | P6: =IF(OR(L6="Utilize_High",L6="Utilize_Med",L6="Utilize_Low"),"Low",IF(L6="No_Change","Med","High")) -> High | Q6: =IF(OR(M6="Utilize_High",M6="Utilize_Med",M6="Utilize_Low"),"Low",IF(M6="No_Change","Med","High")) -> High | R6: =IF(N6=O6,N6,IF(OR(N6="High",O6="High"),"High",IF(OR(N6="Med",O6="Med"),"Med","Low"))) -> Low | S6: =IF(P6=Q6,P6,IF(OR(P6="High",Q6="High"),"High",IF(OR(P6="Med",Q6="Med"),"Med","Low"))) -> High | T6: =VLOOKUP(A6,[1]R2R_N_corridors_Final50!$A$2:$AM$57,39,FALSE) -> Utilize_Low | U6: =VLOOKUP(A6,[1]R2R_N_corridors_Final50!$A$2:$AO$57,41,FALSE) -> Utilize_Low | V6: =VLOOKUP(A6,[1]R2R_N_corridors_Final50!$A$2:$AN$57,40,FALSE) -> Avoid_Med | W6: =VLOOKUP(A6,[1]R2R_N_corridors_Final50!$A$2:$AP$57,42,FALSE) -> Avoid_Med | X6: =IF(OR(T6="Utilize_High",T6="Utilize_Med",T6="Utilize_Low"),"Low",IF(T6="No_Change","Med","High")) -> Low | Y6: =IF(OR(U6="Utilize_High",U6="Utilize_Med",U6="Utilize_Low"),"Low",IF(U6="No_Change","Med","High")) -> Low | Z6: =IF(OR(V6="Utilize_High",V6="Utilize_Med",V6="Utilize_Low"),"Low",IF(V6="No_Change","Med","High")) -> High | AA6: =IF(OR(W6="Utilize_High",W6="Utilize_Med",W6="Utilize_Low"),"Low",IF(W6="No_Change","Med","High")) -> High | AB6: =IF(X6=Y6,X6,IF(OR(X6="High",Y6="High"),"High",IF(OR(X6="Med",Y6="Med"),"Med","Low"))) -> Low | AC6: =IF(Z6=AA6,Z6,IF(OR(Z6="High",AA6="High"),"High",IF(OR(Z6="Med",AA6="Med"),"Med","Low"))) -> High | AD6: =VLOOKUP(A6,MultimodalConnectivity_Corridor!$A$2:$K$57,11,FALSE) -> Low | AE6: =VLOOKUP(A6,[2]METRICS!$AA$2:$AC$70,3,FALSE) -> 8709.6248 | AG6: 1 | AH6: =VLOOKUP(A6,[2]METRICS!$AA$2:$AD$70,4,FALSE) -> 0 | AI6: 0 | AJ6: 99.089982 | AK6: 2.917808 | AL6: 1.9035961 | AM6: 1.0224717 | AN6: 0 | AO6: 1 | AQ6: 356.9 | AR6: 1.3 | AS6: 9 | AT6: Medium
A7: FM0649-KG | B7: 76.826502 | C7: 0.023055081 | D7: 0.023518186 | E7: 1 | G7: 0 | H7: 0 | I7: 0 | J7: Utilize_Med | K7: Utilize_Med | L7: Utilize_High | M7: Utilize_High | N7: =IF(OR(J7="Utilize_High",J7="Utilize_Med",J7="Utilize_Low"),"Low",IF(J7="No_Change","Med","High")) -> Low | O7: =IF(OR(K7="Utilize_High",K7="Utilize_Med",K7="Utilize_Low"),"Low",IF(K7="No_Change","Med","High")) -> Low | P7: =IF(OR(L7="Utilize_High",L7="Utilize_Med",L7="Utilize_Low"),"Low",IF(L7="No_Change","Med","High")) -> Low | Q7: =IF(OR(M7="Utilize_High",M7="Utilize_Med",M7="Utilize_Low"),"Low",IF(M7="No_Change","Med","High")) -> Low | R7: =IF(N7=O7,N7,IF(OR(N7="High",O7="High"),"High",IF(OR(N7="Med",O7="Med"),"Med","Low"))) -> Low | S7: =IF(P7=Q7,P7,IF(OR(P7="High",Q7="High"),"High",IF(OR(P7="Med",Q7="Med"),"Med","Low"))) -> Low | T7: =VLOOKUP(A7,[1]R2R_N_corridors_Final50!$A$2:$AM$57,39,FALSE) -> Utilize_Low | U7: =VLOOKUP(A7,[1]R2R_N_corridors_Final50!$A$2:$AO$57,41,FALSE) -> Utilize_Med | V7: =VLOOKUP(A7,[1]R2R_N_corridors_Final50!$A$2:$AN$57,40,FALSE) -> Utilize_High | W7: =VLOOKUP(A7,[1]R2R_N_corridors_Final50!$A$2:$AP$57,42,FALSE) -> Utilize_High | X7: =IF(OR(T7="Utilize_High",T7="Utilize_Med",T7="Utilize_Low"),"Low",IF(T7="No_Change","Med","High")) -> Low | Y7: =IF(OR(U7="Utilize_High",U7="Utilize_Med",U7="Utilize_Low"),"Low",IF(U7="No_Change","Med","High")) -> Low | Z7: =IF(OR(V7="Utilize_High",V7="Utilize_Med",V7="Utilize_Low"),"Low",IF(V7="No_Change","Med","High")) -> Low | AA7: =IF(OR(W7="Utilize_High",W7="Utilize_Med",W7="Utilize_Low"),"Low",IF(W7="No_Change","Med","High")) -> Low | AB7: =IF(X7=Y7,X7,IF(OR(X7="High",Y7="High"),"High",IF(OR(X7="Med",Y7="Med"),"Med","Low"))) -> Low | AC7: =IF(Z7=AA7,Z7,IF(OR(Z7="High",AA7="High"),"High",IF(OR(Z7="Med",AA7="Med"),"Med","Low"))) -> Low | AD7: =VLOOKUP(A7,MultimodalConnectivity_Corridor!$A$2:$K$57,11,FALSE) -> Low | AE7: =VLOOKUP(A7,[2]METRICS!$AA$2:$AC$70,3,FALSE) -> 11762.504 | AG7: 0 | AH7: =VLOOKUP(A7,[2]METRICS!$AA$2:$AD$70,4,FALSE) -> 6.909667 | AI7: 0 | AJ7: 100 | AK7: 2.309859 | AL7: 1.1376486 | AM7: 1.0216354 | AN7: 0 | AO7: 1 | AQ7: 419.65 | AR7: 2.1 | AS7: 2 | AT7: Medium
A8: FM0650-KG | B8: 3.4067871 | C8: 0 | D8: 0 | E8: 1 | G8: 0 | H8: 0 | I8: 0 | J8: No_Change | K8: No_Change | L8: No_Change | M8: No_Change | N8: =IF(OR(J8="Utilize_High",J8="Utilize_Med",J8="Utilize_Low"),"Low",IF(J8="No_Change","Med","High")) -> Med | O8: =IF(OR(K8="Utilize_High",K8="Utilize_Med",K8="Utilize_Low"),"Low",IF(K8="No_Change","Med","High")) -> Med | P8: =IF(OR(L8="Utilize_High",L8="Utilize_Med",L8="Utilize_Low"),"Low",IF(L8="No_Change","Med","High")) -> Med | Q8: =IF(OR(M8="Utilize_High",M8="Utilize_Med",M8="Utilize_Low"),"Low",IF(M8="No_Change","Med","High")) -> Med | R8: =IF(N8=O8,N8,IF(OR(N8="High",O8="High"),"High",IF(OR(N8="Med",O8="Med"),"Med","Low"))) -> Med | S8: =IF(P8=Q8,P8,IF(OR(P8="High",Q8="High"),"High",IF(OR(P8="Med",Q8="Med"),"Med","Low"))) -> Med | T8: =VLOOKUP(A8,[1]R2R_N_corridors_Final50!$A$2:$AM$57,39,FALSE) -> No_Change | U8: =VLOOKUP(A8,[1]R2R_N_corridors_Final50!$A$2:$AO$57,41,FALSE) -> No_Change | V8: =VLOOKUP(A8,[1]R2R_N_corridors_Final50!$A$2:$AN$57,40,FALSE) -> No_Change | W8: =VLOOKUP(A8,[1]R2R_N_corridors_Final50!$A$2:$AP$57,42,FALSE) -> No_Change | X8: =IF(OR(T8="Utilize_High",T8="Utilize_Med",T8="Utilize_Low"),"Low",IF(T8="No_Change","Med","High")) -> Med | Y8: =IF(OR(U8="Utilize_High",U8="Utilize_Med",U8="Utilize_Low"),"Low",IF(U8="No_Change","Med","High")) -> Med | Z8: =IF(OR(V8="Utilize_High",V8="Utilize_Med",V8="Utilize_Low"),"Low",IF(V8="No_Change","Med","High")) -> Med | AA8: =IF(OR(W8="Utilize_High",W8="Utilize_Med",W8="Utilize_Low"),"Low",IF(W8="No_Change","Med","High")) -> Med | AB8: =IF(X8=Y8,X8,IF(OR(X8="High",Y8="High"),"High",IF(OR(X8="Med",Y8="Med"),"Med","Low"))) -> Med | AC8: =IF(Z8=AA8,Z8,IF(OR(Z8="High",AA8="High"),"High",IF(OR(Z8="Med",AA8="Med"),"Med","Low"))) -> Med | AD8: =VLOOKUP(A8,MultimodalConnectivity_Corridor!$A$2:$K$57,11,FALSE) -> Low | AE8: =VLOOKUP(A8,[2]METRICS!$AA$2:$AC$70,3,FALSE) -> 30777.864 | AG8: 0 | AH8: =VLOOKUP(A8,[2]METRICS!$AA$2:$AD$70,4,FALSE) -> 0 | AI8: 0 | AJ8: 100 | AK8: 7.6 | AL8: 1 | AM8: 1.0149522 | AN8: 0 | AO8: 1 | AQ8: 223.45 | AR8: 0.8 | AS8: 0 | AT8: Medium
A9: FM0681-KG | B9: 27.275757 | C9: 0.069433942 | D9: 0.083122253 | E9: 1 | G9: 0 | H9: 0 | I9: 0 | J9: Utilize_Med | K9: Utilize_Med | L9: Utilize_Med | M9: Utilize_Med | N9: =IF(OR(J9="Utilize_High",J9="Utilize_Med",J9="Utilize_Low"),"Low",IF(J9="No_Change","Med","High")) -> Low | O9: =IF(OR(K9="Utilize_High",K9="Utilize_Med",K9="Utilize_Low"),"Low",IF(K9="No_Change","Med","High")) -> Low | P9: =IF(OR(L9="Utilize_High",L9="Utilize_Med",L9="Utilize_Low"),"Low",IF(L9="No_Change","Med","High")) -> Low | Q9: =IF(OR(M9="Utilize_High",M9="Utilize_Med",M9="Utilize_Low"),"Low",IF(M9="No_Change","Med","High")) -> Low | R9: =IF(N9=O9,N9,IF(OR(N9="High",O9="High"),"High",IF(OR(N9="Med",O9="Med"),"Med","Low"))) -> Low | S9: =IF(P9=Q9,P9,IF(OR(P9="High",Q9="High"),"High",IF(OR(P9="Med",Q9="Med"),"Med","Low"))) -> Low | T9: =VLOOKUP(A9,[1]R2R_N_corridors_Final50!$A$2:$AM$57,39,FALSE) -> Utilize_Med | U9: =VLOOKUP(A9,[1]R2R_N_corridors_Final50!$A$2:$AO$57,41,FALSE) -> Utilize_Med | V9: =VLOOKUP(A9,[1]R2R_N_corridors_Final50!$A$2:$AN$57,40,FALSE) -> Utilize_Med | W9: =VLOOKUP(A9,[1]R2R_N_corridors_Final50!$A$2:$AP$57,42,FALSE) -> Utilize_Med | X9: =IF(OR(T9="Utilize_High",T9="Utilize_Med",T9="Utilize_Low"),"Low",IF(T9="No_Change","Med","High")) -> Low | Y9: =IF(OR(U9="Utilize_High",U9="Utilize_Med",U9="Utilize_Low"),"Low",IF(U9="No_Change","Med","High")) -> Low | Z9: =IF(OR(V9="Utilize_High",V9="Utilize_Med",V9="Utilize_Low"),"Low",IF(V9="No_Change","Med","High")) -> Low | AA9: =IF(OR(W9="Utilize_High",W9="Utilize_Med",W9="Utilize_Low"),"Low",IF(W9="No_Change","Med","High")) -> Low | AB9: =IF(X9=Y9,X9,IF(OR(X9="High",Y9="High"),"High",IF(OR(X9="Med",Y9="Med"),"Med","Low"))) -> Low | AC9: =IF(Z9=AA9,Z9,IF(OR(Z9="High",AA9="High"),"High",IF(OR(Z9="Med",AA9="Med"),"Med","Low"))) -> Low | AD9: =VLOOKUP(A9,MultimodalConnectivity_Corridor!$A$2:$K$57,11,FALSE) -> Low | AE9: =VLOOKUP(A9,[2]METRICS!$AA$2:$AC$70,3,FALSE) -> 629666.78 | AG9: 0 | AH9: =VLOOKUP(A9,[2]METRICS!$AA$2:$AD$70,4,FALSE) -> 0 | AI9: 0 | AJ9: 99.978006 | AK9: 6.925926 | AL9: 1 | AM9: 1 | AN9: 0 | AO9: 1 | AQ9: 525.1 | AR9: 5.2 | AS9: 3 | AT9: Low
A10: FM0755-KG | B10: 60.320466 | C10: 0.069798957 | D10: 0.081901683 | E10: 1 | G10: 0 | H10: 0 | I10: 0 | J10: Avoid_Med | K10: Avoid_Med | L10: Avoid_Med | M10: Avoid_Med | N10: =IF(OR(J10="Utilize_High",J10="Utilize_Med",J10="Utilize_Low"),"Low",IF(J10="No_Change","Med","High")) -> High | O10: =IF(OR(K10="Utilize_High",K10="Utilize_Med",K10="Utilize_Low"),"Low",IF(K10="No_Change","Med","High")) -> High | P10: =IF(OR(L10="Utilize_High",L10="Utilize_Med",L10="Utilize_Low"),"Low",IF(L10="No_Change","Med","High")) -> High | Q10: =IF(OR(M10="Utilize_High",M10="Utilize_Med",M10="Utilize_Low"),"Low",IF(M10="No_Change","Med","High")) -> High | R10: =IF(N10=O10,N10,IF(OR(N10="High",O10="High"),"High",IF(OR(N10="Med",O10="Med"),"Med","Low"))) -> High | S10: =IF(P10=Q10,P10,IF(OR(P10="High",Q10="High"),"High",IF(OR(P10="Med",Q10="Med"),"Med","Low"))) -> High | T10: =VLOOKUP(A10,[1]R2R_N_corridors_Final50!$A$2:$AM$57,39,FALSE) -> Utilize_Med | U10: =VLOOKUP(A10,[1]R2R_N_corridors_Final50!$A$2:$AO$57,41,FALSE) -> Utilize_Med | V10: =VLOOKUP(A10,[1]R2R_N_corridors_Final50!$A$2:$AN$57,40,FALSE) -> Utilize_High | W10: =VLOOKUP(A10,[1]R2R_N_corridors_Final50!$A$2:$AP$57,42,FALSE) -> Utilize_High | X10: =IF(OR(T10="Utilize_High",T10="Utilize_Med",T10="Utilize_Low"),"Low",IF(T10="No_Change","Med","High")) -> Low | Y10: =IF(OR(U10="Utilize_High",U10="Utilize_Med",U10="Utilize_Low"),"Low",IF(U10="No_Change","Med","High")) -> Low | Z10: =IF(OR(V10="Utilize_High",V10="Utilize_Med",V10="Utilize_Low"),"Low",IF(V10="No_Change","Med","High")) -> Low | AA10: =IF(OR(W10="Utilize_High",W10="Utilize_Med",W10="Utilize_Low"),"Low",IF(W10="No_Change","Med","High")) -> Low | AB10: =IF(X10=Y10,X10,IF(OR(X10="High",Y10="High"),"High",IF(OR(X10="Med",Y10="Med"),"Med","Low"))) -> Low | AC10: =IF(Z10=AA10,Z10,IF(OR(Z10="High",AA10="High"),"High",IF(OR(Z10="Med",AA10="Med"),"Med","Low"))) -> Low | AD10: =VLOOKUP(A10,MultimodalConnectivity_Corridor!$A$2:$K$57,11,FALSE) -> Med | AE10: =VLOOKUP(A10,[2]METRICS!$AA$2:$AC$70,3,FALSE) -> 17975.935 | AG10: 0 | AH10: =VLOOKUP(A10,[2]METRICS!$AA$2:$AD$70,4,FALSE) -> 0 | AI10: 0 | AJ10: 92.70038 | AK10: 7.084746 | AL10: 1.9831411 | AM10: 1.0040728 | AN10: 0 | AO10: 1 | AQ10: 447.4 | AR10: 3.1 | AS10: 3 | AT10: High
A11: FM1015-KG | B11: 20.004862 | C11: 0.05362324 | D11: 0.080120369 | E11: 1 | G11: 0 | H11: 0 | I11: 0 | J11: Utilize_Med | K11: Utilize_Med | L11: Utilize_Med | M11: Utilize_Med | N11: =IF(OR(J11="Utilize_High",J11="Utilize_Med",J11="Utilize_Low"),"Low",IF(J11="No_Change","Med","High")) -> Low | O11: =IF(OR(K11="Utilize_High",K11="Utilize_Med",K11="Utilize_Low"),"Low",IF(K11="No_Change","Med","High")) -> Low | P11: =IF(OR(L11="Utilize_High",L11="Utilize_Med",L11="Utilize_Low"),"Low",IF(L11="No_Change","Med","High")) -> Low | Q11: =IF(OR(M11="Utilize_High",M11="Utilize_Med",M11="Utilize_Low"),"Low",IF(M11="No_Change","Med","High")) -> Low | R11: =IF(N11=O11,N11,IF(OR(N11="High",O11="High"),"High",IF(OR(N11="Med",O11="Med"),"Med","Low"))) -> Low | S11: =IF(P11=Q11,P11,IF(OR(P11="High",Q11="High"),"High",IF(OR(P11="Med",Q11="Med"),"Med","Low"))) -> Low | T11: =VLOOKUP(A11,[1]R2R_N_corridors_Final50!$A$2:$AM$57,39,FALSE) -> Utilize_High | U11: =VLOOKUP(A11,[1]R2R_N_corridors_Final50!$A$2:$AO$57,41,FALSE) -> Utilize_High | V11: =VLOOKUP(A11,[1]R2R_N_corridors_Final50!$A$2:$AN$57,40,FALSE) -> Utilize_Med | W11: =VLOOKUP(A11,[1]R2R_N_corridors_Final50!$A$2:$AP$57,42,FALSE) -> Utilize_Med | X11: =IF(OR(T11="Utilize_High",T11="Utilize_Med",T11="Utilize_Low"),"Low",IF(T11="No_Change","Med","High")) -> Low | Y11: =IF(OR(U11="Utilize_High",U11="Utilize_Med",U11="Utilize_Low"),"Low",IF(U11="No_Change","Med","High")) -> Low | Z11: =IF(OR(V11="Utilize_High",V11="Utilize_Med",V11="Utilize_Low"),"Low",IF(V11="No_Change","Med","High")) -> Low | AA11: =IF(OR(W11="Utilize_High",W11="Utilize_Med",W11="Utilize_Low"),"Low",IF(W11="No_Change","Med","High")) -> Low | AB11: =IF(X11=Y11,X11,IF(OR(X11="High",Y11="High"),"High",IF(OR(X11="Med",Y11="Med"),"Med","Low"))) -> Low | AC11: =IF(Z11=AA11,Z11,IF(OR(Z11="High",AA11="High"),"High",IF(OR(Z11="Med",AA11="Med"),"Med","Low"))) -> Low | AD11: =VLOOKUP(A11,MultimodalConnectivity_Corridor!$A$2:$K$57,11,FALSE) -> Low | AE11: =VLOOKUP(A11,[2]METRICS!$AA$2:$AC$70,3,FALSE) -> 522528.69 | AG11: 0 | AH11: =VLOOKUP(A11,[2]METRICS!$AA$2:$AD$70,4,FALSE) -> 0 | AI11: 0 | AJ11: 84.658698 | AK11: 7.6 | AL11: 1.2305779 | AM11: 1.0077614 | AN11: 0 | AO11: 1 | AQ11: 575.05 | AR11: 8.6 | AS11: 3 | AT11: Low
A12: FM1017-KG | B12: 76.142924 | C12: 0.0037508965 | D12: 0.0042141808 | E12: 1 | G12: 0 | H12: 0 | I12: 0 | J12: Utilize_Med | K12: Utilize_Med | L12: Utilize_Med | M12: Utilize_Med | N12: =IF(OR(J12="Utilize_High",J12="Utilize_Med",J12="Utilize_Low"),"Low",IF(J12="No_Change","Med","High")) -> Low | O12: =IF(OR(K12="Utilize_High",K12="Utilize_Med",K12="Utilize_Low"),"Low",IF(K12="No_Change","Med","High")) -> Low | P12: =IF(OR(L12="Utilize_High",L12="Utilize_Med",L12="Utilize_Low"),"Low",IF(L12="No_Change","Med","High")) -> Low | Q12: =IF(OR(M12="Utilize_High",M12="Utilize_Med",M12="Utilize_Low"),"Low",IF(M12="No_Change","Med","High")) -> Low | R12: =IF(N12=O12,N12,IF(OR(N12="High",O12="High"),"High",IF(OR(N12="Med",O12="Med"),"Med","Low"))) -> Low | S12: =IF(P12=Q12,P12,IF(OR(P12="High",Q12="High"),"High",IF(OR(P12="Med",Q12="Med"),"Med","Low"))) -> Low | T12: =VLOOKUP(A12,[1]R2R_N_corridors_Final50!$A$2:$AM$57,39,FALSE) -> Utilize_Low | U12: =VLOOKUP(A12,[1]R2R_N_corridors_Final50!$A$2:$AO$57,41,FALSE) -> Utilize_Low | V12: =VLOOKUP(A12,[1]R2R_N_corridors_Final50!$A$2:$AN$57,40,FALSE) -> Utilize_Med | W12: =VLOOKUP(A12,[1]R2R_N_corridors_Final50!$A$2:$AP$57,42,FALSE) -> Utilize_Med | X12: =IF(OR(T12="Utilize_High",T12="Utilize_Med",T12="Utilize_Low"),"Low",IF(T12="No_Change","Med","High")) -> Low | Y12: =IF(OR(U12="Utilize_High",U12="Utilize_Med",U12="Utilize_Low"),"Low",IF(U12="No_Change","Med","High")) -> Low | Z12: =IF(OR(V12="Utilize_High",V12="Utilize_Med",V12="Utilize_Low"),"Low",IF(V12="No_Change","Med","High")) -> Low | AA12: =IF(OR(W12="Utilize_High",W12="Utilize_Med",W12="Utilize_Low"),"Low",IF(W12="No_Change","Med","High")) -> Low | AB12: =IF(X12=Y12,X12,IF(OR(X12="High",Y12="High"),"High",IF(OR(X12="Med",Y12="Med"),"Med","Low"))) -> Low | AC12: =IF(Z12=AA12,Z12,IF(OR(Z12="High",AA12="High"),"High",IF(OR(Z12="Med",AA12="Med"),"Med","Low"))) -> Low | AD12: =VLOOKUP(A12,MultimodalConnectivity_Corridor!$A$2:$K$57,11,FALSE) -> Med | AE12: =VLOOKUP(A12,[2]METRICS!$AA$2:$AC$70,3,FALSE) -> 27659.271 | AG12: 0 | AH12: =VLOOKUP(A12,[2]METRICS!$AA$2:$AD$70,4,FALSE) -> 0 | AI12: 0 | AJ12: 100 | AK12: 8.486486 | AL12: 1.5301003 | AM12: 1 | AN12: 0 | AO12: 1 | AQ12: 535.7 | AR12: 3.7 | AS12: 4 | AT12: Medium
A13: FM1021-KG | B13: 41.656805 | C13: 0.11145304 | D13: 0.1289041 | E13: 1 | G13: 0 | H13: 0 | I13: 0 | J13: Utilize_Med | K13: Utilize_Med | L13: Avoid_Med | M13: Avoid_Med | N13: =IF(OR(J13="Utilize_High",J13="Utilize_Med",J13="Utilize_Low"),"Low",IF(J13="No_Change","Med","High")) -> Low | O13: =IF(OR(K13="Utilize_High",K13="Utilize_Med",K13="Utilize_Low"),"Low",IF(K13="No_Change","Med","High")) -> Low | P13: =IF(OR(L13="Utilize_High",L13="Utilize_Med",L13="Utilize_Low"),"Low",IF(L13="No_Change","Med","High")) -> High | Q13: =IF(OR(M13="Utilize_High",M13="Utilize_Med",M13="Utilize_Low"),"Low",IF(M13="No_Change","Med","High")) -> High | R13: =IF(N13=O13,N13,IF(OR(N13="High",O13="High"),"High",IF(OR(N13="Med",O13="Med"),"Med","Low"))) -> Low | S13: =IF(P13=Q13,P13,IF(OR(P13="High",Q13="High"),"High",IF(OR(P13="Med",Q13="Med"),"Med","Low"))) -> High | T13: =VLOOKUP(A13,[1]R2R_N_corridors_Final50!$A$2:$AM$57,39,FALSE) -> Utilize_Low | U13: =VLOOKUP(A13,[1]R2R_N_corridors_Final50!$A$2:$AO$57,41,FALSE) -> Utilize_Low | V13: =VLOOKUP(A13,[1]R2R_N_corridors_Final50!$A$2:$AN$57,40,FALSE) -> Avoid_Low | W13: =VLOOKUP(A13,[1]R2R_N_corridors_Final50!$A$2:$AP$57,42,FALSE) -> Avoid_Low | X13: =IF(OR(T13="Utilize_High",T13="Utilize_Med",T13="Utilize_Low"),"Low",IF(T13="No_Change","Med","High")) -> Low | Y13: =IF(OR(U13="Utilize_High",U13="Utilize_Med",U13="Utilize_Low"),"Low",IF(U13="No_Change","Med","High")) -> Low | Z13: =IF(OR(V13="Utilize_High",V13="Utilize_Med",V13="Utilize_Low"),"Low",IF(V13="No_Change","Med","High")) -> High | AA13: =IF(OR(W13="Utilize_High",W13="Utilize_Med",W13="Utilize_Low"),"Low",IF(W13="No_Change","Med","High")) -> High | AB13: =IF(X13=Y13,X13,IF(OR(X13="High",Y13="High"),"High",IF(OR(X13="Med",Y13="Med"),"Med","Low"))) -> Low | AC13: =IF(Z13=AA13,Z13,IF(OR(Z13="High",AA13="High"),"High",IF(OR(Z13="Med",AA13="Med"),"Med","Low"))) -> High | AD13: =VLOOKUP(A13,MultimodalConnectivity_Corridor!$A$2:$K$57,11,FALSE) -> Low | AE13: =VLOOKUP(A13,[2]METRICS!$AA$2:$AC$70,3,FALSE) -> 64.758974 | AG13: 0 | AH13: =VLOOKUP(A13,[2]METRICS!$AA$2:$AD$70,4,FALSE) -> 0 | AI13: 0 | AJ13: 87.052459 | AK13: 5.238095 | AL13: 1.5105739 | AM13: 1.5490925 | AN13: 0 | AO13: 1 | AQ13: 122.5 | AR13: 3.2 | AS13: 3 | AT13: Medium
A14: FM1023-KG | B14: 18.352813 | C14: 0.031123691 | D14: 0.030283543 | E14: 1 | G14: 0 | H14: 43318.667 | I14: 0 | J14: Utilize_Low | K14: Utilize_Low | L14: Avoid_Med | M14: Avoid_Med | N14: =IF(OR(J14="Utilize_High",J14="Utilize_Med",J14="Utilize_Low"),"Low",IF(J14="No_Change","Med","High")) -> Low | O14: =IF(OR(K14="Utilize_High",K14="Utilize_Med",K14="Utilize_Low"),"Low",IF(K14="No_Change","Med","High")) -> Low | P14: =IF(OR(L14="Utilize_High",L14="Utilize_Med",L14="Utilize_Low"),"Low",IF(L14="No_Change","Med","High")) -> High | Q14: =IF(OR(M14="Utilize_High",M14="Utilize_Med",M14="Utilize_Low"),"Low",IF(M14="No_Change","Med","High")) -> High | R14: =IF(N14=O14,N14,IF(OR(N14="High",O14="High"),"High",IF(OR(N14="Med",O14="Med"),"Med","Low"))) -> Low | S14: =IF(P14=Q14,P14,IF(OR(P14="High",Q14="High"),"High",IF(OR(P14="Med",Q14="Med"),"Med","Low"))) -> High | T14: =VLOOKUP(A14,[1]R2R_N_corridors_Final50!$A$2:$AM$57,39,FALSE) -> Utilize_Low | U14: =VLOOKUP(A14,[1]R2R_N_corridors_Final50!$A$2:$AO$57,41,FALSE) -> Utilize_Low | V14: =VLOOKUP(A14,[1]R2R_N_corridors_Final50!$A$2:$AN$57,40,FALSE) -> Avoid_Med | W14: =VLOOKUP(A14,[1]R2R_N_corridors_Final50!$A$2:$AP$57,42,FALSE) -> Avoid_Med | X14: =IF(OR(T14="Utilize_High",T14="Utilize_Med",T14="Utilize_Low"),"Low",IF(T14="No_Change","Med","High")) -> Low | Y14: =IF(OR(U14="Utilize_High",U14="Utilize_Med",U14="Utilize_Low"),"Low",IF(U14="No_Change","Med","High")) -> Low | Z14: =IF(OR(V14="Utilize_High",V14="Utilize_Med",V14="Utilize_Low"),"Low",IF(V14="No_Change","Med","High")) -> High | AA14: =IF(OR(W14="Utilize_High",W14="Utilize_Med",W14="Utilize_Low"),"Low",IF(W14="No_Change","Med","High")) -> High | AB14: =IF(X14=Y14,X14,IF(OR(X14="High",Y14="High"),"High",IF(OR(X14="Med",Y14="Med"),"Med","Low"))) -> Low | AC14: =IF(Z14=AA14,Z14,IF(OR(Z14="High",AA14="High"),"High",IF(OR(Z14="Med",AA14="Med"),"Med","Low"))) -> High | AD14: =VLOOKUP(A14,MultimodalConnectivity_Corridor!$A$2:$K$57,11,FALSE) -> High | AE14: =VLOOKUP(A14,[2]METRICS!$AA$2:$AC$70,3,FALSE) -> 1010.1164 | AG14: 0 | AH14: =VLOOKUP(A14,[2]METRICS!$AA$2:$AD$70,4,FALSE) -> 0 | AI14: 0 | AJ14: 86.868532 | AK14: 3 | AL14: 1 | AM14: 1 | AN14: 0 | AO14: 1 | AQ14: 331.65 | AR14: 4.1 | AS14: 5 | AT14: High
... A58: US0385-KG | B58: 97.141263 | C58: 0.089422396 | D58: 0.10766483 | E58: 1 | G58: 2.125449 | H58: 2391.8473 | I58: 1210.895 | J58: Avoid_Low | K58: Avoid_Low | L58: Avoid_High | M58: Avoid_High | N58: =IF(OR(J58="Utilize_High",J58="Utilize_Med",J58="Utilize_Low"),"Low",IF(J58="No_Change","Med","High")) -> High | O58: =IF(OR(K58="Utilize_High",K58="Utilize_Med",K58="Utilize_Low"),"Low",IF(K58="No_Change","Med","High")) -> High | P58: =IF(OR(L58="Utilize_High",L58="Utilize_Med",L58="Utilize_Low"),"Low",IF(L58="No_Change","Med","High")) -> High | Q58: =IF(OR(M58="Utilize_High",M58="Utilize_Med",M58="Utilize_Low"),"Low",IF(M58="No_Change","Med","High")) -> High | R58: =IF(N58=O58,N58,IF(OR(N58="High",O58="High"),"High",IF(OR(N58="Med",O58="Med"),"Med","Low"))) -> High | S58: =IF(P58=Q58,P58,IF(OR(P58="High",Q58="High"),"High",IF(OR(P58="Med",Q58="Med"),"Med","Low"))) -> High | T58: =VLOOKUP(A58,[1]R2R_N_corridors_Final50!$A$2:$AM$57,39,FALSE) -> Avoid_Low | U58: =VLOOKUP(A58,[1]R2R_N_corridors_Final50!$A$2:$AO$57,41,FALSE) -> Avoid_Low | V58: =VLOOKUP(A58,[1]R2R_N_corridors_Final50!$A$2:$AN$57,40,FALSE) -> Avoid_High | W58: =VLOOKUP(A58,[1]R2R_N_corridors_Final50!$A$2:$AP$57,42,FALSE) -> Avoid_High | X58: =IF(OR(T58="Utilize_High",T58="Utilize_Med",T58="Utilize_Low"),"Low",IF(T58="No_Change","Med","High")) -> High | Y58: =IF(OR(U58="Utilize_High",U58="Utilize_Med",U58="Utilize_Low"),"Low",IF(U58="No_Change","Med","High")) -> High | Z58: =IF(OR(V58="Utilize_High",V58="Utilize_Med",V58="Utilize_Low"),"Low",IF(V58="No_Change","Med","High")) -> High | AA58: =IF(OR(W58="Utilize_High",W58="Utilize_Med",W58="Utilize_Low"),"Low",IF(W58="No_Change","Med","High")) -> High | AB58: =IF(X58=Y58,X58,IF(OR(X58="High",Y58="High"),"High",IF(OR(X58="Med",Y58="Med"),"Med","Low"))) -> High | AC58: =IF(Z58=AA58,Z58,IF(OR(Z58="High",AA58="High"),"High",IF(OR(Z58="Med",AA58="Med"),"Med","Low"))) -> High | AD58: =VLOOKUP(A58,MultimodalConnectivity_Corridor!$A$2:$K$57,11,FALSE) -> Med | AE58: =VLOOKUP(A58,[2]METRICS!$AA$2:$AC$70,3,FALSE) -> 9416.6644 | AG58: 1 | AH58: =VLOOKUP(A58,[2]METRICS!$AA$2:$AD$70,4,FALSE) -> 2.611485 | AI58: 0 | AJ58: 62.757091 | AK58: 9.284768 | AL58: 1.0774793 | AM58: 1.0023432 | AN58: 0 | AO58: 1 | AQ58: 178.25 | AR58: 2.3 | AS58: 4 | AT58: Medium

Sheet data_CLEAN
C1: mobility, reliability, and connectvity | M1: safety and security | O1: asset preservation and technology deployment | V1: customer service, stewardship and sustainability, and equity
A2: corridor_j | B2: Miles | C2: existing vc | D2: forecasted vc | E2: TTRI | F2: delay_psgr_s_corr | G2: delay_trk_s_corr | H2: PV_Inefficiency_22 | I2: Trk_Inefficiency_22 | J2: PV_Inefficiency_50 | K2: Trk_Inefficiency_50 | L2: Multimodal | M2: Safety | N2: RR_crash | O2: frontage roads | P2: % lane mileage with 2 or less lanes | Q2: shoulder width | R2: Pavement Conditions | S2: Bridge Condition | T2: 16' bridge or lower | U2: ITS | V2: access to historic, cultural, and tourist activities | W2: EV charging inventory and proximity | X2: access to rest areas/truck parking | Y2: Equity
A3: 240AA1005 | B3: 12.562325 | C3: 0 | D3: 0 | E3: 0 | F3: 0 | G3: 0 | H3: Med | I3: Med | J3: Med | K3: Med | L3: =VLOOKUP(A3,MultimodalConnectivity_Corridor!$A$2:$K$57,11,FALSE) -> Low | M3: =VLOOKUP(A3,[2]METRICS!$AA$2:$AC$70,3,FALSE) -> 0 | N3: =VLOOKUP(A3,[2]METRICS!$AA$2:$AD$70,4,FALSE) -> 0 | O3: 0 | P3: 100 | Q3: 0 | R3: 1 | S3: 2.5482162 | T3: 0 | U3: 1 | V3: 209 | W3: 1.4 | X3: 2 | Y3: Low
A4: FM0305-KG | B4: 19.554896 | C4: 0.089692533 | D4: 0.11675096 | E4: 0 | F4: 0 | G4: 0 | H4: High | I4: High | J4: High | K4: High | L4: =VLOOKUP(A4,MultimodalConnectivity_Corridor!$A$2:$K$57,11,FALSE) -> Low | M4: =VLOOKUP(A4,[2]METRICS!$AA$2:$AC$70,3,FALSE) -> 8479.4644 | N4: =VLOOKUP(A4,[2]METRICS!$AA$2:$AD$70,4,FALSE) -> 0 | O4: 0 | P4: 89.065645 | Q4: 6.605263 | R4: 1.1051689 | S4: 1.0008768 | T4: 0 | U4: 1.0499296 | V4: 101.45 | W4: 0.2 | X4: 2 | Y4: Med
A5: FM0490-KG | B5: 13.986049 | C5: 0.045740773 | D5: 0.06815768 | E5: 0 | F5: 0 | G5: 0 | H5: Low | I5: Low | J5: Low | K5: Low | L5: =VLOOKUP(A5,MultimodalConnectivity_Corridor!$A$2:$K$57,11,FALSE) -> Low | M5: =VLOOKUP(A5,[2]METRICS!$AA$2:$AC$70,3,FALSE) -> 8375.8624 | N5: =VLOOKUP(A5,[2]METRICS!$AA$2:$AD$70,4,FALSE) -> 0.010102 | O5: 0 | P5: 100 | Q5: 3 | R5: 1.0780987 | S5: 1.0006469 | T5: 0 | U5: 1 | V5: 516.1 | W5: 5.9 | X5: 3 | Y5: Low
A6: FM0624-KG | B6: 97.643794 | C6: 0.046073154 | D6: 0.042790414 | E6: 0 | F6: 0 | G6: 0 | H6: Low | I6: High | J6: Low | K6: High | L6: =VLOOKUP(A6,MultimodalConnectivity_Corridor!$A$2:$K$57,11,FALSE) -> Low | M6: =VLOOKUP(A6,[2]METRICS!$AA$2:$AC$70,3,FALSE) -> 8709.6248 | N6: =VLOOKUP(A6,[2]METRICS!$AA$2:$AD$70,4,FALSE) -> 0 | O6: 0 | P6: 99.089982 | Q6: 2.917808 | R6: 1.9035961 | S6: 1.0224717 | T6: 0 | U6: 1 | V6: 356.9 | W6: 1.3 | X6: 9 | Y6: Med
A7: FM0649-KG | B7: 76.826502 | C7: 0.023055081 | D7: 0.023518186 | E7: 0 | F7: 0 | G7: 0 | H7: Low | I7: Low | J7: Low | K7: Low | L7: =VLOOKUP(A7,MultimodalConnectivity_Corridor!$A$2:$K$57,11,FALSE) -> Low | M7: =VLOOKUP(A7,[2]METRICS!$AA$2:$AC$70,3,FALSE) -> 11762.504 | N7: =VLOOKUP(A7,[2]METRICS!$AA$2:$AD$70,4,FALSE) -> 6.909667 | O7: 0 | P7: 100 | Q7: 2.309859 | R7: 1.1376486 | S7: 1.0216354 | T7: 0 | U7: 1 | V7: 419.65 | W7: 2.1 | X7: 2 | Y7: Med
A8: FM0650-KG | B8: 3.4067871 | C8: 0 | D8: 0 | E8: 0 | F8: 0 | G8: 0 | H8: Med | I8: Med | J8: Med | K8: Med | L8: =VLOOKUP(A8,MultimodalConnectivity_Corridor!$A$2:$K$57,11,FALSE) -> Low | M8: =VLOOKUP(A8,[2]METRICS!$AA$2:$AC$70,3,FALSE) -> 30777.864 | N8: =VLOOKUP(A8,[2]METRICS!$AA$2:$AD$70,4,FALSE) -> 0 | O8: 0 | P8: 100 | Q8: 7.6 | R8: 1 | S8: 1.0149522 | T8: 0 | U8: 1 | V8: 223.45 | W8: 0.8 | X8: 0 | Y8: Med
A9: FM0681-KG | B9: 27.275757 | C9: 0.069433942 | D9: 0.083122253 | E9: 0 | F9: 0 | G9: 0 | H9: Low | I9: Low | J9: Low | K9: Low | L9: =VLOOKUP(A9,MultimodalConnectivity_Corridor!$A$2:$K$57,11,FALSE) -> Low | M9: =VLOOKUP(A9,[2]METRICS!$AA$2:$AC$70,3,FALSE) -> 629666.78 | N9: =VLOOKUP(A9,[2]METRICS!$AA$2:$AD$70,4,FALSE) -> 0 | O9: 0 | P9: 99.978006 | Q9: 6.925926 | R9: 1 | S9: 1 | T9: 0 | U9: 1 | V9: 525.1 | W9: 5.2 | X9: 3 | Y9: Low
A10: FM0755-KG | B10: 60.320466 | C10: 0.069798957 | D10: 0.081901683 | E10: 0 | F10: 0 | G10: 0 | H10: High | I10: High | J10: Low | K10: Low | L10: =VLOOKUP(A10,MultimodalConnectivity_Corridor!$A$2:$K$57,11,FALSE) -> Med | M10: =VLOOKUP(A10,[2]METRICS!$AA$2:$AC$70,3,FALSE) -> 17975.935 | N10: =VLOOKUP(A10,[2]METRICS!$AA$2:$AD$70,4,FALSE) -> 0 | O10: 0 | P10: 92.70038 | Q10: 7.084746 | R10: 1.9831411 | S10: 1.0040728 | T10: 0 | U10: 1 | V10: 447.4 | W10: 3.1 | X10: 3 | Y10: High
A11: FM1015-KG | B11: 20.004862 | C11: 0.05362324 | D11: 0.080120369 | E11: 0 | F11: 0 | G11: 0 | H11: Low | I11: Low | J11: Low | K11: Low | L11: =VLOOKUP(A11,MultimodalConnectivity_Corridor!$A$2:$K$57,11,FALSE) -> Low | M11: =VLOOKUP(A11,[2]METRICS!$AA$2:$AC$70,3,FALSE) -> 522528.69 | N11: =VLOOKUP(A11,[2]METRICS!$AA$2:$AD$70,4,FALSE) -> 0 | O11: 0 | P11: 84.658698 | Q11: 7.6 | R11: 1.2305779 | S11: 1.0077614 | T11: 0 | U11: 1 | V11: 575.05 | W11: 8.6 | X11: 3 | Y11: Low
A12: FM1017-KG | B12: 76.142924 | C12: 0.0037508965 | D12: 0.0042141808 | E12: 0 | F12: 0 | G12: 0 | H12: Low | I12: Low | J12: Low | K12: Low | L12: =VLOOKUP(A12,MultimodalConnectivity_Corridor!$A$2:$K$57,11,FALSE) -> Med | M12: =VLOOKUP(A12,[2]METRICS!$AA$2:$AC$70,3,FALSE) -> 27659.271 | N12: =VLOOKUP(A12,[2]METRICS!$AA$2:$AD$70,4,FALSE) -> 0 | O12: 0 | P12: 100 | Q12: 8.486486 | R12: 1.5301003 | S12: 1 | T12: 0 | U12: 1 | V12: 535.7 | W12: 3.7 | X12: 4 | Y12: Med
A13: FM1021-KG | B13: 41.656805 | C13: 0.11145304 | D13: 0.1289041 | E13: 0 | F13: 0 | G13: 0 | H13: Low | I13: High | J13: Low | K13: High | L13: =VLOOKUP(A13,MultimodalConnectivity_Corridor!$A$2:$K$57,11,FALSE) -> Low | M13: =VLOOKUP(A13,[2]METRICS!$AA$2:$AC$70,3,FALSE) -> 64.758974 | N13: =VLOOKUP(A13,[2]METRICS!$AA$2:$AD$70,4,FALSE) -> 0 | O13: 0 | P13: 87.052459 | Q13: 5.238095 | R13: 1.5105739 | S13: 1.5490925 | T13: 0 | U13: 1 | V13: 122.5 | W13: 3.2 | X13: 3 | Y13: Med
A14: FM1023-KG | B14: 18.352813 | C14: 0.031123691 | D14: 0.030283543 | E14: 0 | F14: 43318.667 | G14: 0 | H14: Low | I14: High | J14: Low | K14: High | L14: =VLOOKUP(A14,MultimodalConnectivity_Corridor!$A$2:$K$57,11,FALSE) -> High | M14: =VLOOKUP(A14,[2]METRICS!$AA$2:$AC$70,3,FALSE) -> 1010.1164 | N14: =VLOOKUP(A14,[2]METRICS!$AA$2:$AD$70,4,FALSE) -> 0 | O14: 0 | P14: 86.868532 | Q14: 3 | R14: 1 | S14: 1 | T14: 0 | U14: 1 | V14: 331.65 | W14: 4.1 | X14: 5 | Y14: High
... A58: US0385-KG | B58: 97.141263 | C58: 0.089422396 | D58: 0.10766483 | E58: 2.125449 | F58: 2391.8473 | G58: 1210.895 | H58: High | I58: High | J58: High | K58: High | L58: =VLOOKUP(A58,MultimodalConnectivity_Corridor!$A$2:$K$57,11,FALSE) -> Med | M58: =VLOOKUP(A58,[2]METRICS!$AA$2:$AC$70,3,FALSE) -> 9416.6644 | N58: =VLOOKUP(A58,[2]METRICS!$AA$2:$AD$70,4,FALSE) -> 2.611485 | O58: 0 | P58: 62.757091 | Q58: 9.284768 | R58: 1.0774793 | S58: 1.0023432 | T58: 0 | U58: 1 | V58: 178.25 | W58: 2.3 | X58: 4 | Y58: Med

Sheet data_SCORING
C1: mobility, reliability, and connectvity | M1: safety and security | O1: asset preservation and technology deployment | V1: customer service, stewardship and sustainability, and equity
A2: corridor_j | B2: Miles | C2: existing vc | D2: forecasted vc | E2: TTRI | F2: delay_psgr_s_corr | G2: delay_trk_s_corr | H2: PV_Inefficiency_22 | I2: Trk_Inefficiency_22 | J2: PV_Inefficiency_50 | K2: Trk_Inefficiency_50 | L2: Multimodal | M2: Safety | N2: RR_crash | O2: frontage roads | P2: % lane mileage with 2 or less lanes | Q2: shoulder width | R2: Pavement Conditions | S2: Bridge Condition | T2: 16' bridge or lower | U2: ITS | V2: access to historic, cultural, and tourist activities | W2: EV charging inventory and proximity | X2: access to rest areas/truck parking | Y2: Equity | Z2: mob_rel_con_score | AA2: safe_sec_score | AB2: asst_pres_tech_score | AC2: cust_stew_sust_eq_score | AD2: final_score
A3: 240AA1005 | B3: 12.562325 | C3: =IF(data_CLEAN!C3<=SCORE_METHOD!$B$7,SCORE_METHOD!$N$6,IF(data_CLEAN!C3<=SCORE_METHOD!$B$8,SCORE_METHOD!$N$7,SCORE_METHOD!$N$8)) -> 1 | D3: =IF(data_CLEAN!D3<=SCORE_METHOD!$C$7,SCORE_METHOD!$N$6,IF(data_CLEAN!D3<=SCORE_METHOD!$C$8,SCORE_METHOD!$N$7,SCORE_METHOD!$N$8)) -> 1 | E3: =IF(data_CLEAN!E3<=SCORE_METHOD!$D$7,SCORE_METHOD!$N$6,IF(data_CLEAN!E3<=SCORE_METHOD!$D$8,SCORE_METHOD!$N$7,SCORE_METHOD!$N$8)) -> 1 | F3: =IF(data_CLEAN!F3<=SCORE_METHOD!$E$7,SCORE_METHOD!$N$6,IF(data_CLEAN!F3<=SCORE_METHOD!$E$8,SCORE_METHOD!$N$7,SCORE_METHOD!$N$8)) -> 1 | G3: =IF(data_CLEAN!G3<=SCORE_METHOD!$F$7,SCORE_METHOD!$N$6,IF(data_CLEAN!G3<=SCORE_METHOD!$F$8,SCORE_METHOD!$N$7,SCORE_METHOD!$N$8)) -> 1 | H3: =VLOOKUP(data_CLEAN!H3,SCORE_METHOD!$A$13:$B$15,2,FALSE) -> 2 | I3: =VLOOKUP(data_CLEAN!I3,SCORE_METHOD!$A$13:$C$15,3,FALSE) -> 2 | J3: =VLOOKUP(data_CLEAN!J3,SCORE_METHOD!$A$13:$D$15,4,FALSE) -> 2 | K3: =VLOOKUP(data_CLEAN!K3,SCORE_METHOD!$A$13:$E$15,5,FALSE) -> 2 | L3: =VLOOKUP(data_CLEAN!L3,SCORE_METHOD!$A$19:$B$21,2,FALSE) -> 3 | M3: =IF(data_CLEAN!M3<=SCORE_METHOD!$G$7,SCORE_METHOD!$N$6,IF(data_CLEAN!M3<=SCORE_METHOD!$G$8,SCORE_METHOD!$N$7,SCORE_METHOD!$N$8)) -> 1 | N3: =IF(data_CLEAN!N3<=SCORE_METHOD!$H$7,SCORE_METHOD!$N$6,IF(data_CLEAN!N3<=SCORE_METHOD!$H$8,SCORE_METHOD!$N$7,SCORE_METHOD!$N$8)) -> 1 | O3: =VLOOKUP(data_CLEAN!O3,SCORE_METHOD!$A$25:$C$26,3,FALSE) -> 1 | P3: =IF(data_CLEAN!P3<=SCORE_METHOD!$I$7,SCORE_METHOD!$N$6,IF(data_CLEAN!P3<=SCORE_METHOD!$I$8,SCORE_METHOD!$N$7,SCORE_METHOD!$N$8)) -> 3 | Q3: =IF(data_CLEAN!Q3<=SCORE_METHOD!$B$31,SCORE_METHOD!$C$30,IF(data_CLEAN!Q3<=SCORE_METHOD!$B$32,SCORE_METHOD!$C$31,SCORE_METHOD!$C$32)) -> 3 | R3: =IF(data_CLEAN!R3<=SCORE_METHOD!$J$7,SCORE_METHOD!$N$6,IF(data_CLEAN!S3<=SCORE_METHOD!$J$8,SCORE_METHOD!$N$7,SCORE_METHOD!$N$8)) -> 1 | S3: =IF(data_CLEAN!S3<=SCORE_METHOD!$D$31,SCORE_METHOD!$E$30,IF(data_CLEAN!S3<=SCORE_METHOD!$D$32,SCORE_METHOD!$E$31,SCORE_METHOD!$E$32)) -> 1 | T3: =VLOOKUP(data_CLEAN!T3,SCORE_METHOD!$A$25:$E$26,5,FALSE) -> 0 | U3: =IF(data_CLEAN!U3=1,SCORE_METHOD!$B$37,SCORE_METHOD!$B$38) -> 1 | V3: =IF(data_CLEAN!V3<=SCORE_METHOD!$K$7,SCORE_METHOD!$N$6,IF(data_CLEAN!V3<=SCORE_METHOD!$K$8,SCORE_METHOD!$N$7,SCORE_METHOD!$N$8)) -> 1 | W3: =IF(data_CLEAN!W3<=SCORE_METHOD!$L$7,SCORE_METHOD!$N$6,IF(data_CLEAN!W3<=SCORE_METHOD!$L$8,SCORE_METHOD!$N$7,SCORE_METHOD!$N$8)) -> 1 | X3: =IF(data_CLEAN!X3<=SCORE_METHOD!$M$7,SCORE_METHOD!$N$6,IF(data_CLEAN!X3<=SCORE_METHOD!$M$8,SCORE_METHOD!$N$7,SCORE_METHOD!$N$8)) -> 1 | Y3: =VLOOKUP(data_CLEAN!Y3,SCORE_METHOD!$A$13:$F$15,6,FALSE) -> 1 | Z3: =SUM(C3:L3)*SCORE_METHOD!$E$53 -> 1.6 | AA3: =SUM(M3:N3)*SCORE_METHOD!$E$63 -> 1 | AB3: =SUM(O3:U3)*SCORE_METHOD!$E$65 -> 1.4285714 | AC3: =SUM(V3:Y3)*SCORE_METHOD!$E$72 -> 1 | AD3: =Z3*SCORE_METHOD!$C$44+data_SCORING!AA3*SCORE_METHOD!$C$45+data_SCORING!AB3*SCORE_METHOD!$C$46+data_SCORING!AC3*SCORE_METHOD!$C$47 -> 1.2571429
A4: FM0305-KG | B4: 19.554896 | C4: =IF(data_CLEAN!C4<=SCORE_METHOD!$B$7,SCORE_METHOD!$N$6,IF(data_CLEAN!C4<=SCORE_METHOD!$B$8,SCORE_METHOD!$N$7,SCORE_METHOD!$N$8)) -> 3 | D4: =IF(data_CLEAN!D4<=SCORE_METHOD!$C$7,SCORE_METHOD!$N$6,IF(data_CLEAN!D4<=SCORE_METHOD!$C$8,SCORE_METHOD!$N$7,SCORE_METHOD!$N$8)) -> 3 | E4: =IF(data_CLEAN!E4<=SCORE_METHOD!$D$7,SCORE_METHOD!$N$6,IF(data_CLEAN!E4<=SCORE_METHOD!$D$8,SCORE_METHOD!$N$7,SCORE_METHOD!$N$8)) -> 1 | F4: =IF(data_CLEAN!F4<=SCORE_METHOD!$E$7,SCORE_METHOD!$N$6,IF(data_CLEAN!F4<=SCORE_METHOD!$E$8,SCORE_METHOD!$N$7,SCORE_METHOD!$N$8)) -> 1 | G4: =IF(data_CLEAN!G4<=SCORE_METHOD!$F$7,SCORE_METHOD!$N$6,IF(data_CLEAN!G4<=SCORE_METHOD!$F$8,SCORE_METHOD!$N$7,SCORE_METHOD!$N$8)) -> 1 | H4: =VLOOKUP(data_CLEAN!H4,SCORE_METHOD!$A$13:$B$15,2,FALSE) -> 3 | I4: =VLOOKUP(data_CLEAN!I4,SCORE_METHOD!$A$13:$C$15,3,FALSE) -> 3 | J4: =VLOOKUP(data_CLEAN!J4,SCORE_METHOD!$A$13:$D$15,4,FALSE) -> 3 | K4: =VLOOKUP(data_CLEAN!K4,SCORE_METHOD!$A$13:$E$15,5,FALSE) -> 3 | L4: =VLOOKUP(data_CLEAN!L4,SCORE_METHOD!$A$19:$B$21,2,FALSE) -> 3 | M4: =IF(data_CLEAN!M4<=SCORE_METHOD!$G$7,SCORE_METHOD!$N$6,IF(data_CLEAN!M4<=SCORE_METHOD!$G$8,SCORE_METHOD!$N$7,SCORE_METHOD!$N$8)) -> 2 | N4: =IF(data_CLEAN!N4<=SCORE_METHOD!$H$7,SCORE_METHOD!$N$6,IF(data_CLEAN!N4<=SCORE_METHOD!$H$8,SCORE_METHOD!$N$7,SCORE_METHOD!$N$8)) -> 1 | O4: =VLOOKUP(data_CLEAN!O4,SCORE_METHOD!$A$25:$C$26,3,FALSE) -> 1 | P4: =IF(data_CLEAN!P4<=SCORE_METHOD!$I$7,SCORE_METHOD!$N$6,IF(data_CLEAN!P4<=SCORE_METHOD!$I$8,SCORE_METHOD!$N$7,SCORE_METHOD!$N$8)) -> 2 | Q4: =IF(data_CLEAN!Q4<=SCORE_METHOD!$B$31,SCORE_METHOD!$C$30,IF(data_CLEAN!Q4<=SCORE_METHOD!$B$32,SCORE_METHOD!$C$31,SCORE_METHOD!$C$32)) -> 2 | R4: =IF(data_CLEAN!R4<=SCORE_METHOD!$J$7,SCORE_METHOD!$N$6,IF(data_CLEAN!S4<=SCORE_METHOD!$J$8,SCORE_METHOD!$N$7,SCORE_METHOD!$N$8)) -> 2 | S4: =IF(data_CLEAN!S4<=SCORE_METHOD!$D$31,SCORE_METHOD!$E$30,IF(data_CLEAN!S4<=SCORE_METHOD!$D$32,SCORE_METHOD!$E$31,SCORE_METHOD!$E$32)) -> 3 | T4: =VLOOKUP(data_CLEAN!T4,SCORE_METHOD!$A$25:$E$26,5,FALSE) -> 0 | U4: =IF(data_CLEAN!U4=1,SCORE_METHOD!$B$37,SCORE_METHOD!$B$38) -> 0 | V4: =IF(data_CLEAN!V4<=SCORE_METHOD!$K$7,SCORE_METHOD!$N$6,IF(data_CLEAN!V4<=SCORE_METHOD!$K$8,SCORE_METHOD!$N$7,SCORE_METHOD!$N$8)) -> 1 | W4: =IF(data_CLEAN!W4<=SCORE_METHOD!$L$7,SCORE_METHOD!$N$6,IF(data_CLEAN!W4<=SCORE_METHOD!$L$8,SCORE_METHOD!$N$7,SCORE_METHOD!$N$8)) -> 1 | X4: =IF(data_CLEAN!X4<=SCORE_METHOD!$M$7,SCORE_METHOD!$N$6,IF(data_CLEAN!X4<=SCORE_METHOD!$M$8,SCORE_METHOD!$N$7,SCORE_METHOD!$N$8)) -> 1 | Y4: =VLOOKUP(data_CLEAN!Y4,SCORE_METHOD!$A$13:$F$15,6,FALSE) -> 2 | Z4: =SUM(C4:L4)*SCORE_METHOD!$E$53 -> 2.4 | AA4: =SUM(M4:N4)*SCORE_METHOD!$E$63 -> 1.5 | AB4: =SUM(O4:U4)*SCORE_METHOD!$E$65 -> 1.4285714 | AC4: =SUM(V4:Y4)*SCORE_METHOD!$E$72 -> 1.25 | AD4: =Z4*SCORE_METHOD!$C$44+data_SCORING!AA4*SCORE_METHOD!$C$45+data_SCORING!AB4*SCORE_METHOD!$C$46+data_SCORING!AC4*SCORE_METHOD!$C$47 -> 1.6446429
A5: FM0490-KG | B5: 13.986049 | C5: =IF(data_CLEAN!C5<=SCORE_METHOD!$B$7,SCORE_METHOD!$N$6,IF(data_CLEAN!C5<=SCORE_METHOD!$B$8,SCORE_METHOD!$N$7,SCORE_METHOD!$N$8)) -> 2 | D5: =IF(data_CLEAN!D5<=SCORE_METHOD!$C$7,SCORE_METHOD!$N$6,IF(data_CLEAN!D5<=SCORE_METHOD!$C$8,SCORE_METHOD!$N$7,SCORE_METHOD!$N$8)) -> 2 | E5: =IF(data_CLEAN!E5<=SCORE_METHOD!$D$7,SCORE_METHOD!$N$6,IF(data_CLEAN!E5<=SCORE_METHOD!$D$8,SCORE_METHOD!$N$7,SCORE_METHOD!$N$8)) -> 1 | F5: =IF(data_CLEAN!F5<=SCORE_METHOD!$E$7,SCORE_METHOD!$N$6,IF(data_CLEAN!F5<=SCORE_METHOD!$E$8,SCORE_METHOD!$N$7,SCORE_METHOD!$N$8)) -> 1 | G5: =IF(data_CLEAN!G5<=SCORE_METHOD!$F$7,SCORE_METHOD!$N$6,IF(data_CLEAN!G5<=SCORE_METHOD!$F$8,SCORE_METHOD!$N$7,SCORE_METHOD!$N$8)) -> 1 | H5: =VLOOKUP(data_CLEAN!H5,SCORE_METHOD!$A$13:$B$15,2,FALSE) -> 1 | I5: =VLOOKUP(data_CLEAN!I5,SCORE_METHOD!$A$13:$C$15,3,FALSE) -> 1 | J5: =VLOOKUP(data_CLEAN!J5,SCORE_METHOD!$A$13:$D$15,4,FALSE) -> 1 | K5: =VLOOKUP(data_CLEAN!K5,SCORE_METHOD!$A$13:$E$15,5,FALSE) -> 1 | L5: =VLOOKUP(data_CLEAN!L5,SCORE_METHOD!$A$19:$B$21,2,FALSE) -> 3 | M5: =IF(data_CLEAN!M5<=SCORE_METHOD!$G$7,SCORE_METHOD!$N$6,IF(data_CLEAN!M5<=SCORE_METHOD!$G$8,SCORE_METHOD!$N$7,SCORE_METHOD!$N$8)) -> 2 | N5: =IF(data_CLEAN!N5<=SCORE_METHOD!$H$7,SCORE_METHOD!$N$6,IF(data_CLEAN!N5<=SCORE_METHOD!$H$8,SCORE_METHOD!$N$7,SCORE_METHOD!$N$8)) -> 2 | O5: =VLOOKUP(data_CLEAN!O5,SCORE_METHOD!$A$25:$C$26,3,FALSE) -> 1 | P5: =IF(data_CLEAN!P5<=SCORE_METHOD!$I$7,SCORE_METHOD!$N$6,IF(data_CLEAN!P5<=SCORE_METHOD!$I$8,SCORE_METHOD!$N$7,SCORE_METHOD!$N$8)) -> 3 | Q5: =IF(data_CLEAN!Q5<=SCORE_METHOD!$B$31,SCORE_METHOD!$C$30,IF(data_CLEAN!Q5<=SCORE_METHOD!$B$32,SCORE_METHOD!$C$31,SCORE_METHOD!$C$32)) -> 3 | R5: =IF(data_CLEAN!R5<=SCORE_METHOD!$J$7,SCORE_METHOD!$N$6,IF(data_CLEAN!S5<=SCORE_METHOD!$J$8,SCORE_METHOD!$N$7,SCORE_METHOD!$N$8)) -> 2 | S5: =IF(data_CLEAN!S5<=SCORE_METHOD!$D$31,SCORE_METHOD!$E$30,IF(data_CLEAN!S5<=SCORE_METHOD!$D$32,SCORE_METHOD!$E$31,SCORE_METHOD!$E$32)) -> 3 | T5: =VLOOKUP(data_CLEAN!T5,SCORE_METHOD!$A$25:$E$26,5,FALSE) -> 0 | U5: =IF(data_CLEAN!U5=1,SCORE_METHOD!$B$37,SCORE_METHOD!$B$38) -> 1 | V5: =IF(data_CLEAN!V5<=SCORE_METHOD!$K$7,SCORE_METHOD!$N$6,IF(data_CLEAN!V5<=SCORE_METHOD!$K$8,SCORE_METHOD!$N$7,SCORE_METHOD!$N$8)) -> 3 | W5: =IF(data_CLEAN!W5<=SCORE_METHOD!$L$7,SCORE_METHOD!$N$6,IF(data_CLEAN!W5<=SCORE_METHOD!$L$8,SCORE_METHOD!$N$7,SCORE_METHOD!$N$8)) -> 3 | X5: =IF(data_CLEAN!X5<=SCORE_METHOD!$M$7,SCORE_METHOD!$N$6,IF(data_CLEAN!X5<=SCORE_METHOD!$M$8,SCORE_METHOD!$N$7,SCORE_METHOD!$N$8)) -> 1 | Y5: =VLOOKUP(data_CLEAN!Y5,SCORE_METHOD!$A$13:$F$15,6,FALSE) -> 1 | Z5: =SUM(C5:L5)*SCORE_METHOD!$E$53 -> 1.4 | AA5: =SUM(M5:N5)*SCORE_METHOD!$E$63 -> 2 | AB5: =SUM(O5:U5)*SCORE_METHOD!$E$65 -> 1.8571429 | AC5: =SUM(V5:Y5)*SCORE_METHOD!$E$72 -> 2 | AD5: =Z5*SCORE_METHOD!$C$44+data_SCORING!AA5*SCORE_METHOD!$C$45+data_SCORING!AB5*SCORE_METHOD!$C$46+data_SCORING!AC5*SCORE_METHOD!$C$47 -> 1.8142857
A6: FM0624-KG | B6: 97.643794 | C6: =IF(data_CLEAN!C6<=SCORE_METHOD!$B$7,SCORE_METHOD!$N$6,IF(data_CLEAN!C6<=SCORE_METHOD!$B$8,SCORE_METHOD!$N$7,SCORE_METHOD!$N$8)) -> 2 | D6: =IF(data_CLEAN!D6<=SCORE_METHOD!$C$7,SCORE_METHOD!$N$6,IF(data_CLEAN!D6<=SCORE_METHOD!$C$8,SCORE_METHOD!$N$7,SCORE_METHOD!$N$8)) -> 2 | E6: =IF(data_CLEAN!E6<=SCORE_METHOD!$D$7,SCORE_METHOD!$N$6,IF(data_CLEAN!E6<=SCORE_METHOD!$D$8,SCORE_METHOD!$N$7,SCORE_METHOD!$N$8)) -> 1 | F6: =IF(data_CLEAN!F6<=SCORE_METHOD!$E$7,SCORE_METHOD!$N$6,IF(data_CLEAN!F6<=SCORE_METHOD!$E$8,SCORE_METHOD!$N$7,SCORE_METHOD!$N$8)) -> 1 | G6: =IF(data_CLEAN!G6<=SCORE_METHOD!$F$7,SCORE_METHOD!$N$6,IF(data_CLEAN!G6<=SCORE_METHOD!$F$8,SCORE_METHOD!$N$7,SCORE_METHOD!$N$8)) -> 1 | H6: =VLOOKUP(data_CLEAN!H6,SCORE_METHOD!$A$13:$B$15,2,FALSE) -> 1 | I6: =VLOOKUP(data_CLEAN!I6,SCORE_METHOD!$A$13:$C$15,3,FALSE) -> 3 | J6: =VLOOKUP(data_CLEAN!J6,SCORE_METHOD!$A$13:$D$15,4,FALSE) -> 1 | K6: =VLOOKUP(data_CLEAN!K6,SCORE_METHOD!$A$13:$E$15,5,FALSE) -> 3 | L6: =VLOOKUP(data_CLEAN!L6,SCORE_METHOD!$A$19:$B$21,2,FALSE) -> 3 | M6: =IF(data_CLEAN!M6<=SCORE_METHOD!$G$7,SCORE_METHOD!$N$6,IF(data_CLEAN!M6<=SCORE_METHOD!$G$8,SCORE_METHOD!$N$7,SCORE_METHOD!$N$8)) -> 2 | N6: =IF(data_CLEAN!N6<=SCORE_METHOD!$H$7,SCORE_METHOD!$N$6,IF(data_CLEAN!N6<=SCORE_METHOD!$H$8,SCORE_METHOD!$N$7,SCORE_METHOD!$N$8)) -> 1 | O6: =VLOOKUP(data_CLEAN!O6,SCORE_METHOD!$A$25:$C$26,3,FALSE) -> 1 | P6: =IF(data_CLEAN!P6<=SCORE_METHOD!$I$7,SCORE_METHOD!$N$6,IF(data_CLEAN!P6<=SCORE_METHOD!$I$8,SCORE_METHOD!$N$7,SCORE_METHOD!$N$8)) -> 3 | Q6: =IF(data_CLEAN!Q6<=SCORE_METHOD!$B$31,SCORE_METHOD!$C$30,IF(data_CLEAN!Q6<=SCORE_METHOD!$B$32,SCORE_METHOD!$C$31,SCORE_METHOD!$C$32)) -> 3 | R6: =IF(data_CLEAN!R6<=SCORE_METHOD!$J$7,SCORE_METHOD!$N$6,IF(data_CLEAN!S6<=SCORE_METHOD!$J$8,SCORE_METHOD!$N$7,SCORE_METHOD!$N$8)) -> 2 | S6: =IF(data_CLEAN!S6<=SCORE_METHOD!$D$31,SCORE_METHOD!$E$30,IF(data_CLEAN!S6<=SCORE_METHOD!$D$32,SCORE_METHOD!$E$31,SCORE_METHOD!$E$32)) -> 2 | T6: =VLOOKUP(data_CLEAN!T6,SCORE_METHOD!$A$25:$E$26,5,FALSE) -> 0 | U6: =IF(data_CLEAN!U6=1,SCORE_METHOD!$B$37,SCORE_METHOD!$B$38) -> 1 | V6: =IF(data_CLEAN!V6<=SCORE_METHOD!$K$7,SCORE_METHOD!$N$6,IF(data_CLEAN!V6<=SCORE_METHOD!$K$8,SCORE_METHOD!$N$7,SCORE_METHOD!$N$8)) -> 2 | W6: =IF(data_CLEAN!W6<=SCORE_METHOD!$L$7,SCORE_METHOD!$N$6,IF(data_CLEAN!W6<=SCORE_METHOD!$L$8,SCORE_METHOD!$N$7,SCORE_METHOD!$N$8)) -> 1 | X6: =IF(data_CLEAN!X6<=SCORE_METHOD!$M$7,SCORE_METHOD!$N$6,IF(data_CLEAN!X6<=SCORE_METHOD!$M$8,SCORE_METHOD!$N$7,SCORE_METHOD!$N$8)) -> 3 | Y6: =VLOOKUP(data_CLEAN!Y6,SCORE_METHOD!$A$13:$F$15,6,FALSE) -> 2 | Z6: =SUM(C6:L6)*SCORE_METHOD!$E$53 -> 1.8 | AA6: =SUM(M6:N6)*SCORE_METHOD!$E$63 -> 1.5 | AB6: =SUM(O6:U6)*SCORE_METHOD!$E$65 -> 1.7142857 | AC6: =SUM(V6:Y6)*SCORE_METHOD!$E$72 -> 2 | AD6: =Z6*SCORE_METHOD!$C$44+data_SCORING!AA6*SCORE_METHOD!$C$45+data_SCORING!AB6*SCORE_METHOD!$C$46+data_SCORING!AC6*SCORE_METHOD!$C$47 -> 1.7535714
A7: FM0649-KG | B7: 76.826502 | C7: =IF(data_CLEAN!C7<=SCORE_METHOD!$B$7,SCORE_METHOD!$N$6,IF(data_CLEAN!C7<=SCORE_METHOD!$B$8,SCORE_METHOD!$N$7,SCORE_METHOD!$N$8)) -> 1 | D7: =IF(data_CLEAN!D7<=SCORE_METHOD!$C$7,SCORE_METHOD!$N$6,IF(data_CLEAN!D7<=SCORE_METHOD!$C$8,SCORE_METHOD!$N$7,SCORE_METHOD!$N$8)) -> 1 | E7: =IF(data_CLEAN!E7<=SCORE_METHOD!$D$7,SCORE_METHOD!$N$6,IF(data_CLEAN!E7<=SCORE_METHOD!$D$8,SCORE_METHOD!$N$7,SCORE_METHOD!$N$8)) -> 1 | F7: =IF(data_CLEAN!F7<=SCORE_METHOD!$E$7,SCORE_METHOD!$N$6,IF(data_CLEAN!F7<=SCORE_METHOD!$E$8,SCORE_METHOD!$N$7,SCORE_METHOD!$N$8)) -> 1 | G7: =IF(data_CLEAN!G7<=SCORE_METHOD!$F$7,SCORE_METHOD!$N$6,IF(data_CLEAN!G7<=SCORE_METHOD!$F$8,SCORE_METHOD!$N$7,SCORE_METHOD!$N$8)) -> 1 | H7: =VLOOKUP(data_CLEAN!H7,SCORE_METHOD!$A$13:$B$15,2,FALSE) -> 1 | I7: =VLOOKUP(data_CLEAN!I7,SCORE_METHOD!$A$13:$C$15,3,FALSE) -> 1 | J7: =VLOOKUP(data_CLEAN!J7,SCORE_METHOD!$A$13:$D$15,4,FALSE) -> 1 | K7: =VLOOKUP(data_CLEAN!K7,SCORE_METHOD!$A$13:$E$15,5,FALSE) -> 1 | L7: =VLOOKUP(data_CLEAN!L7,SCORE_METHOD!$A$19:$B$21,2,FALSE) -> 3 | M7: =IF(data_CLEAN!M7<=SCORE_METHOD!$G$7,SCORE_METHOD!$N$6,IF(data_CLEAN!M7<=SCORE_METHOD!$G$8,SCORE_METHOD!$N$7,SCORE_METHOD!$N$8)) -> 2 | N7: =IF(data_CLEAN!N7<=SCORE_METHOD!$H$7,SCORE_METHOD!$N$6,IF(data_CLEAN!N7<=SCORE_METHOD!$H$8,SCORE_METHOD!$N$7,SCORE_METHOD!$N$8)) -> 3 | O7: =VLOOKUP(data_CLEAN!O7,SCORE_METHOD!$A$25:$C$26,3,FALSE) -> 1 | P7: =IF(data_CLEAN!P7<=SCORE_METHOD!$I$7,SCORE_METHOD!$N$6,IF(data_CLEAN!P7<=SCORE_METHOD!$I$8,SCORE_METHOD!$N$7,SCORE_METHOD!$N$8)) -> 3 | Q7: =IF(data_CLEAN!Q7<=SCORE_METHOD!$B$31,SCORE_METHOD!$C$30,IF(data_CLEAN!Q7<=SCORE_METHOD!$B$32,SCORE_METHOD!$C$31,SCORE_METHOD!$C$32)) -> 3 | R7: =IF(data_CLEAN!R7<=SCORE_METHOD!$J$7,SCORE_METHOD!$N$6,IF(data_CLEAN!S7<=SCORE_METHOD!$J$8,SCORE_METHOD!$N$7,SCORE_METHOD!$N$8)) -> 2 | S7: =IF(data_CLEAN!S7<=SCORE_METHOD!$D$31,SCORE_METHOD!$E$30,IF(data_CLEAN!S7<=SCORE_METHOD!$D$32,SCORE_METHOD!$E$31,SCORE_METHOD!$E$32)) -> 2 | T7: =VLOOKUP(data_CLEAN!T7,SCORE_METHOD!$A$25:$E$26,5,FALSE) -> 0 | U7: =IF(data_CLEAN!U7=1,SCORE_METHOD!$B$37,SCORE_METHOD!$B$38) -> 1 | V7: =IF(data_CLEAN!V7<=SCORE_METHOD!$K$7,SCORE_METHOD!$N$6,IF(data_CLEAN!V7<=SCORE_METHOD!$K$8,SCORE_METHOD!$N$7,SCORE_METHOD!$N$8)) -> 3 | W7: =IF(data_CLEAN!W7<=SCORE_METHOD!$L$7,SCORE_METHOD!$N$6,IF(data_CLEAN!W7<=SCORE_METHOD!$L$8,SCORE_METHOD!$N$7,SCORE_METHOD!$N$8)) -> 1 | X7: =IF(data_CLEAN!X7<=SCORE_METHOD!$M$7,SCORE_METHOD!$N$6,IF(data_CLEAN!X7<=SCORE_METHOD!$M$8,SCORE_METHOD!$N$7,SCORE_METHOD!$N$8)) -> 1 | Y7: =VLOOKUP(data_CLEAN!Y7,SCORE_METHOD!$A$13:$F$15,6,FALSE) -> 2 | Z7: =SUM(C7:L7)*SCORE_METHOD!$E$53 -> 1.2 | AA7: =SUM(M7:N7)*SCORE_METHOD!$E$63 -> 2.5 | AB7: =SUM(O7:U7)*SCORE_METHOD!$E$65 -> 1.7142857 | AC7: =SUM(V7:Y7)*SCORE_METHOD!$E$72 -> 1.75 | AD7: =Z7*SCORE_METHOD!$C$44+data_SCORING!AA7*SCORE_METHOD!$C$45+data_SCORING!AB7*SCORE_METHOD!$C$46+data_SCORING!AC7*SCORE_METHOD!$C$47 -> 1.7910714
A8: FM0650-KG | B8: 3.4067871 | C8: =IF(data_CLEAN!C8<=SCORE_METHOD!$B$7,SCORE_METHOD!$N$6,IF(data_CLEAN!C8<=SCORE_METHOD!$B$8,SCORE_METHOD!$N$7,SCORE_METHOD!$N$8)) -> 1 | D8: =IF(data_CLEAN!D8<=SCORE_METHOD!$C$7,SCORE_METHOD!$N$6,IF(data_CLEAN!D8<=SCORE_METHOD!$C$8,SCORE_METHOD!$N$7,SCORE_METHOD!$N$8)) -> 1 | E8: =IF(data_CLEAN!E8<=SCORE_METHOD!$D$7,SCORE_METHOD!$N$6,IF(data_CLEAN!E8<=SCORE_METHOD!$D$8,SCORE_METHOD!$N$7,SCORE_METHOD!$N$8)) -> 1 | F8: =IF(data_CLEAN!F8<=SCORE_METHOD!$E$7,SCORE_METHOD!$N$6,IF(data_CLEAN!F8<=SCORE_METHOD!$E$8,SCORE_METHOD!$N$7,SCORE_METHOD!$N$8)) -> 1 | G8: =IF(data_CLEAN!G8<=SCORE_METHOD!$F$7,SCORE_METHOD!$N$6,IF(data_CLEAN!G8<=SCORE_METHOD!$F$8,SCORE_METHOD!$N$7,SCORE_METHOD!$N$8)) -> 1 | H8: =VLOOKUP(data_CLEAN!H8,SCORE_METHOD!$A$13:$B$15,2,FALSE) -> 2 | I8: =VLOOKUP(data_CLEAN!I8,SCORE_METHOD!$A$13:$C$15,3,FALSE) -> 2 | J8: =VLOOKUP(data_CLEAN!J8,SCORE_METHOD!$A$13:$D$15,4,FALSE) -> 2 | K8: =VLOOKUP(data_CLEAN!K8,SCORE_METHOD!$A$13:$E$15,5,FALSE) -> 2 | L8: =VLOOKUP(data_CLEAN!L8,SCORE_METHOD!$A$19:$B$21,2,FALSE) -> 3 | M8: =IF(data_CLEAN!M8<=SCORE_METHOD!$G$7,SCORE_METHOD!$N$6,IF(data_CLEAN!M8<=SCORE_METHOD!$G$8,SCORE_METHOD!$N$7,SCORE_METHOD!$N$8)) -> 3 | N8: =IF(data_CLEAN!N8<=SCORE_METHOD!$H$7,SCORE_METHOD!$N$6,IF(data_CLEAN!N8<=SCORE_METHOD!$H$8,SCORE_METHOD!$N$7,SCORE_METHOD!$N$8)) -> 1 | O8: =VLOOKUP(data_CLEAN!O8,SCORE_METHOD!$A$25:$C$26,3,FALSE) -> 1 | P8: =IF(data_CLEAN!P8<=SCORE_METHOD!$I$7,SCORE_METHOD!$N$6,IF(data_CLEAN!P8<=SCORE_METHOD!$I$8,SCORE_METHOD!$N$7,SCORE_METHOD!$N$8)) -> 3 | Q8: =IF(data_CLEAN!Q8<=SCORE_METHOD!$B$31,SCORE_METHOD!$C$30,IF(data_CLEAN!Q8<=SCORE_METHOD!$B$32,SCORE_METHOD!$C$31,SCORE_METHOD!$C$32)) -> 2 | R8: =IF(data_CLEAN!R8<=SCORE_METHOD!$J$7,SCORE_METHOD!$N$6,IF(data_CLEAN!S8<=SCORE_METHOD!$J$8,SCORE_METHOD!$N$7,SCORE_METHOD!$N$8)) -> 1 | S8: =IF(data_CLEAN!S8<=SCORE_METHOD!$D$31,SCORE_METHOD!$E$30,IF(data_CLEAN!S8<=SCORE_METHOD!$D$32,SCORE_METHOD!$E$31,SCORE_METHOD!$E$32)) -> 2 | T8: =VLOOKUP(data_CLEAN!T8,SCORE_METHOD!$A$25:$E$26,5,FALSE) -> 0 | U8: =IF(data_CLEAN!U8=1,SCORE_METHOD!$B$37,SCORE_METHOD!$B$38) -> 1 | V8: =IF(data_CLEAN!V8<=SCORE_METHOD!$K$7,SCORE_METHOD!$N$6,IF(data_CLEAN!V8<=SCORE_METHOD!$K$8,SCORE_METHOD!$N$7,SCORE_METHOD!$N$8)) -> 1 | W8: =IF(data_CLEAN!W8<=SCORE_METHOD!$L$7,SCORE_METHOD!$N$6,IF(data_CLEAN!W8<=SCORE_METHOD!$L$8,SCORE_METHOD!$N$7,SCORE_METHOD!$N$8)) -> 1 | X8: =IF(data_CLEAN!X8<=SCORE_METHOD!$M$7,SCORE_METHOD!$N$6,IF(data_CLEAN!X8<=SCORE_METHOD!$M$8,SCORE_METHOD!$N$7,SCORE_METHOD!$N$8)) -> 1 | Y8: =VLOOKUP(data_CLEAN!Y8,SCORE_METHOD!$A$13:$F$15,6,FALSE) -> 2 | Z8: =SUM(C8:L8)*SCORE_METHOD!$E$53 -> 1.6 | AA8: =SUM(M8:N8)*SCORE_METHOD!$E$63 -> 2 | AB8: =SUM(O8:U8)*SCORE_METHOD!$E$65 -> 1.4285714 | AC8: =SUM(V8:Y8)*SCORE_METHOD!$E$72 -> 1.25 | AD8: =Z8*SCORE_METHOD!$C$44+data_SCORING!AA8*SCORE_METHOD!$C$45+data_SCORING!AB8*SCORE_METHOD!$C$46+data_SCORING!AC8*SCORE_METHOD!$C$47 -> 1.5696429
A9: FM0681-KG | B9: 27.275757 | C9: =IF(data_CLEAN!C9<=SCORE_METHOD!$B$7,SCORE_METHOD!$N$6,IF(data_CLEAN!C9<=SCORE_METHOD!$B$8,SCORE_METHOD!$N$7,SCORE_METHOD!$N$8)) -> 2 | D9: =IF(data_CLEAN!D9<=SCORE_METHOD!$C$7,SCORE_METHOD!$N$6,IF(data_CLEAN!D9<=SCORE_METHOD!$C$8,SCORE_METHOD!$N$7,SCORE_METHOD!$N$8)) -> 2 | E9: =IF(data_CLEAN!E9<=SCORE_METHOD!$D$7,SCORE_METHOD!$N$6,IF(data_CLEAN!E9<=SCORE_METHOD!$D$8,SCORE_METHOD!$N$7,SCORE_METHOD!$N$8)) -> 1 | F9: =IF(data_CLEAN!F9<=SCORE_METHOD!$E$7,SCORE_METHOD!$N$6,IF(data_CLEAN!F9<=SCORE_METHOD!$E$8,SCORE_METHOD!$N$7,SCORE_METHOD!$N$8)) -> 1 | G9: =IF(data_CLEAN!G9<=SCORE_METHOD!$F$7,SCORE_METHOD!$N$6,IF(data_CLEAN!G9<=SCORE_METHOD!$F$8,SCORE_METHOD!$N$7,SCORE_METHOD!$N$8)) -> 1 | H9: =VLOOKUP(data_CLEAN!H9,SCORE_METHOD!$A$13:$B$15,2,FALSE) -> 1 | I9: =VLOOKUP(data_CLEAN!I9,SCORE_METHOD!$A$13:$C$15,3,FALSE) -> 1 | J9: =VLOOKUP(data_CLEAN!J9,SCORE_METHOD!$A$13:$D$15,4,FALSE) -> 1 | K9: =VLOOKUP(data_CLEAN!K9,SCORE_METHOD!$A$13:$E$15,5,FALSE) -> 1 | L9: =VLOOKUP(data_CLEAN!L9,SCORE_METHOD!$A$19:$B$21,2,FALSE) -> 3 | M9: =IF(data_CLEAN!M9<=SCORE_METHOD!$G$7,SCORE_METHOD!$N$6,IF(data_CLEAN!M9<=SCORE_METHOD!$G$8,SCORE_METHOD!$N$7,SCORE_METHOD!$N$8)) -> 3 | N9: =IF(data_CLEAN!N9<=SCORE_METHOD!$H$7,SCORE_METHOD!$N$6,IF(data_CLEAN!N9<=SCORE_METHOD!$H$8,SCORE_METHOD!$N$7,SCORE_METHOD!$N$8)) -> 1 | O9: =VLOOKUP(data_CLEAN!O9,SCORE_METHOD!$A$25:$C$26,3,FALSE) -> 1 | P9: =IF(data_CLEAN!P9<=SCORE_METHOD!$I$7,SCORE_METHOD!$N$6,IF(data_CLEAN!P9<=SCORE_METHOD!$I$8,SCORE_METHOD!$N$7,SCORE_METHOD!$N$8)) -> 3 | Q9: =IF(data_CLEAN!Q9<=SCORE_METHOD!$B$31,SCORE_METHOD!$C$30,IF(data_CLEAN!Q9<=SCORE_METHOD!$B$32,SCORE_METHOD!$C$31,SCORE_METHOD!$C$32)) -> 2 | R9: =IF(data_CLEAN!R9<=SCORE_METHOD!$J$7,SCORE_METHOD!$N$6,IF(data_CLEAN!S9<=SCORE_METHOD!$J$8,SCORE_METHOD!$N$7,SCORE_METHOD!$N$8)) -> 1 | S9: =IF(data_CLEAN!S9<=SCORE_METHOD!$D$31,SCORE_METHOD!$E$30,IF(data_CLEAN!S9<=SCORE_METHOD!$D$32,SCORE_METHOD!$E$31,SCORE_METHOD!$E$32)) -> 3 | T9: =VLOOKUP(data_CLEAN!T9,SCORE_METHOD!$A$25:$E$26,5,FALSE) -> 0 | U9: =IF(data_CLEAN!U9=1,SCORE_METHOD!$B$37,SCORE_METHOD!$B$38) -> 1 | V9: =IF(data_CLEAN!V9<=SCORE_METHOD!$K$7,SCORE_METHOD!$N$6,IF(data_CLEAN!V9<=SCORE_METHOD!$K$8,SCORE_METHOD!$N$7,SCORE_METHOD!$N$8)) -> 3 | W9: =IF(data_CLEAN!W9<=SCORE_METHOD!$L$7,SCORE_METHOD!$N$6,IF(data_CLEAN!W9<=SCORE_METHOD!$L$8,SCORE_METHOD!$N$7,SCORE_METHOD!$N$8)) -> 3 | X9: =IF(data_CLEAN!X9<=SCORE_METHOD!$M$7,SCORE_METHOD!$N$6,IF(data_CLEAN!X9<=SCORE_METHOD!$M$8,SCORE_METHOD!$N$7,SCORE_METHOD!$N$8)) -> 1 | Y9: =VLOOKUP(data_CLEAN!Y9,SCORE_METHOD!$A$13:$F$15,6,FALSE) -> 1 | Z9: =SUM(C9:L9)*SCORE_METHOD!$E$53 -> 1.4 | AA9: =SUM(M9:N9)*SCORE_METHOD!$E$63 -> 2 | AB9: =SUM(O9:U9)*SCORE_METHOD!$E$65 -> 1.5714286 | AC9: =SUM(V9:Y9)*SCORE_METHOD!$E$72 -> 2 | AD9: =Z9*SCORE_METHOD!$C$44+data_SCORING!AA9*SCORE_METHOD!$C$45+data_SCORING!AB9*SCORE_METHOD!$C$46+data_SCORING!AC9*SCORE_METHOD!$C$47 -> 1.7428571
A10: FM0755-KG | B10: 60.320466 | C10: =IF(data_CLEAN!C10<=SCORE_METHOD!$B$7,SCORE_METHOD!$N$6,IF(data_CLEAN!C10<=SCORE_METHOD!$B$8,SCORE_METHOD!$N$7,SCORE_METHOD!$N$8)) -> 2 | D10: =IF(data_CLEAN!D10<=SCORE_METHOD!$C$7,SCORE_METHOD!$N$6,IF(data_CLEAN!D10<=SCORE_METHOD!$C$8,SCORE_METHOD!$N$7,SCORE_METHOD!$N$8)) -> 2 | E10: =IF(data_CLEAN!E10<=SCORE_METHOD!$D$7,SCORE_METHOD!$N$6,IF(data_CLEAN!E10<=SCORE_METHOD!$D$8,SCORE_METHOD!$N$7,SCORE_METHOD!$N$8)) -> 1 | F10: =IF(data_CLEAN!F10<=SCORE_METHOD!$E$7,SCORE_METHOD!$N$6,IF(data_CLEAN!F10<=SCORE_METHOD!$E$8,SCORE_METHOD!$N$7,SCORE_METHOD!$N$8)) -> 1 | G10: =IF(data_CLEAN!G10<=SCORE_METHOD!$F$7,SCORE_METHOD!$N$6,IF(data_CLEAN!G10<=SCORE_METHOD!$F$8,SCORE_METHOD!$N$7,SCORE_METHOD!$N$8)) -> 1 | H10: =VLOOKUP(data_CLEAN!H10,SCORE_METHOD!$A$13:$B$15,2,FALSE) -> 3 | I10: =VLOOKUP(data_CLEAN!I10,SCORE_METHOD!$A$13:$C$15,3,FALSE) -> 3 | J10: =VLOOKUP(data_CLEAN!J10,SCORE_METHOD!$A$13:$D$15,4,FALSE) -> 1 | K10: =VLOOKUP(data_CLEAN!K10,SCORE_METHOD!$A$13:$E$15,5,FALSE) -> 1 | L10: =VLOOKUP(data_CLEAN!L10,SCORE_METHOD!$A$19:$B$21,2,FALSE) -> 2 | M10: =IF(data_CLEAN!M10<=SCORE_METHOD!$G$7,SCORE_METHOD!$N$6,IF(data_CLEAN!M10<=SCORE_METHOD!$G$8,SCORE_METHOD!$N$7,SCORE_METHOD!$N$8)) -> 2 | N10: =IF(data_CLEAN!N10<=SCORE_METHOD!$H$7,SCORE_METHOD!$N$6,IF(data_CLEAN!N10<=SCORE_METHOD!$H$8,SCORE_METHOD!$N$7,SCORE_METHOD!$N$8)) -> 1 | O10: =VLOOKUP(data_CLEAN!O10,SCORE_METHOD!$A$25:$C$26,3,FALSE) -> 1 | P10: =IF(data_CLEAN!P10<=SCORE_METHOD!$I$7,SCORE_METHOD!$N$6,IF(data_CLEAN!P10<=SCORE_METHOD!$I$8,SCORE_METHOD!$N$7,SCORE_METHOD!$N$8)) -> 2 | Q10: =IF(data_CLEAN!Q10<=SCORE_METHOD!$B$31,SCORE_METHOD!$C$30,IF(data_CLEAN!Q10<=SCORE_METHOD!$B$32,SCORE_METHOD!$C$31,SCORE_METHOD!$C$32)) -> 2 | R10: =IF(data_CLEAN!R10<=SCORE_METHOD!$J$7,SCORE_METHOD!$N$6,IF(data_CLEAN!S10<=SCORE_METHOD!$J$8,SCORE_METHOD!$N$7,SCORE_METHOD!$N$8)) -> 2 | S10: =IF(data_CLEAN!S10<=SCORE_METHOD!$D$31,SCORE_METHOD!$E$30,IF(data_CLEAN!S10<=SCORE_METHOD!$D$32,SCORE_METHOD!$E$31,SCORE_METHOD!$E$32)) -> 3 | T10: =VLOOKUP(data_CLEAN!T10,SCORE_METHOD!$A$25:$E$26,5,FALSE) -> 0 | U10: =IF(data_CLEAN!U10=1,SCORE_METHOD!$B$37,SCORE_METHOD!$B$38) -> 1 | V10: =IF(data_CLEAN!V10<=SCORE_METHOD!$K$7,SCORE_METHOD!$N$6,IF(data_CLEAN!V10<=SCORE_METHOD!$K$8,SCORE_METHOD!$N$7,SCORE_METHOD!$N$8)) -> 3 | W10: =IF(data_CLEAN!W10<=SCORE_METHOD!$L$7,SCORE_METHOD!$N$6,IF(data_CLEAN!W10<=SCORE_METHOD!$L$8,SCORE_METHOD!$N$7,SCORE_METHOD!$N$8)) -> 2 | X10: =IF(data_CLEAN!X10<=SCORE_METHOD!$M$7,SCORE_METHOD!$N$6,IF(data_CLEAN!X10<=SCORE_METHOD!$M$8,SCORE_METHOD!$N$7,SCORE_METHOD!$N$8)) -> 1 | Y10: =VLOOKUP(data_CLEAN!Y10,SCORE_METHOD!$A$13:$F$15,6,FALSE) -> 3 | Z10: =SUM(C10:L10)*SCORE_METHOD!$E$53 -> 1.7 | AA10: =SUM(M10:N10)*SCORE_METHOD!$E$63 -> 1.5 | AB10: =SUM(O10:U10)*SCORE_METHOD!$E$65 -> 1.5714286 | AC10: =SUM(V10:Y10)*SCORE_METHOD!$E$72 -> 2.25 | AD10: =Z10*SCORE_METHOD!$C$44+data_SCORING!AA10*SCORE_METHOD!$C$45+data_SCORING!AB10*SCORE_METHOD!$C$46+data_SCORING!AC10*SCORE_METHOD!$C$47 -> 1.7553571
A11: FM1015-KG | B11: 20.004862 | C11: =IF(data_CLEAN!C11<=SCORE_METHOD!$B$7,SCORE_METHOD!$N$6,IF(data_CLEAN!C11<=SCORE_METHOD!$B$8,SCORE_METHOD!$N$7,SCORE_METHOD!$N$8)) -> 2 | D11: =IF(data_CLEAN!D11<=SCORE_METHOD!$C$7,SCORE_METHOD!$N$6,IF(data_CLEAN!D11<=SCORE_METHOD!$C$8,SCORE_METHOD!$N$7,SCORE_METHOD!$N$8)) -> 2 | E11: =IF(data_CLEAN!E11<=SCORE_METHOD!$D$7,SCORE_METHOD!$N$6,IF(data_CLEAN!E11<=SCORE_METHOD!$D$8,SCORE_METHOD!$N$7,SCORE_METHOD!$N$8)) -> 1 | F11: =IF(data_CLEAN!F11<=SCORE_METHOD!$E$7,SCORE_METHOD!$N$6,IF(data_CLEAN!F11<=SCORE_METHOD!$E$8,SCORE_METHOD!$N$7,SCORE_METHOD!$N$8)) -> 1 | G11: =IF(data_CLEAN!G11<=SCORE_METHOD!$F$7,SCORE_METHOD!$N$6,IF(data_CLEAN!G11<=SCORE_METHOD!$F$8,SCORE_METHOD!$N$7,SCORE_METHOD!$N$8)) -> 1 | H11: =VLOOKUP(data_CLEAN!H11,SCORE_METHOD!$A$13:$B$15,2,FALSE) -> 1 | I11: =VLOOKUP(data_CLEAN!I11,SCORE_METHOD!$A$13:$C$15,3,FALSE) -> 1 | J11: =VLOOKUP(data_CLEAN!J11,SCORE_METHOD!$A$13:$D$15,4,FALSE) -> 1 | K11: =VLOOKUP(data_CLEAN!K11,SCORE_METHOD!$A$13:$E$15,5,FALSE) -> 1 | L11: =VLOOKUP(data_CLEAN!L11,SCORE_METHOD!$A$19:$B$21,2,FALSE) -> 3 | M11: =IF(data_CLEAN!M11<=SCORE_METHOD!$G$7,SCORE_METHOD!$N$6,IF(data_CLEAN!M11<=SCORE_METHOD!$G$8,SCORE_METHOD!$N$7,SCORE_METHOD!$N$8)) -> 3 | N11: =IF(data_CLEAN!N11<=SCORE_METHOD!$H$7,SCORE_METHOD!$N$6,IF(data_CLEAN!N11<=SCORE_METHOD!$H$8,SCORE_METHOD!$N$7,SCORE_METHOD!$N$8)) -> 1 | O11: =VLOOKUP(data_CLEAN!O11,SCORE_METHOD!$A$25:$C$26,3,FALSE) -> 1 | P11: =IF(data_CLEAN!P11<=SCORE_METHOD!$I$7,SCORE_METHOD!$N$6,IF(data_CLEAN!P11<=SCORE_METHOD!$I$8,SCORE_METHOD!$N$7,SCORE_METHOD!$N$8)) -> 2 | Q11: =IF(data_CLEAN!Q11<=SCORE_METHOD!$B$31,SCORE_METHOD!$C$30,IF(data_CLEAN!Q11<=SCORE_METHOD!$B$32,SCORE_METHOD!$C$31,SCORE_METHOD!$C$32)) -> 2 | R11: =IF(data_CLEAN!R11<=SCORE_METHOD!$J$7,SCORE_METHOD!$N$6,IF(data_CLEAN!S11<=SCORE_METHOD!$J$8,SCORE_METHOD!$N$7,SCORE_METHOD!$N$8)) -> 2 | S11: =IF(data_CLEAN!S11<=SCORE_METHOD!$D$31,SCORE_METHOD!$E$30,IF(data_CLEAN!S11<=SCORE_METHOD!$D$32,SCORE_METHOD!$E$31,SCORE_METHOD!$E$32)) -> 3 | T11: =VLOOKUP(data_CLEAN!T11,SCORE_METHOD!$A$25:$E$26,5,FALSE) -> 0 | U11: =IF(data_CLEAN!U11=1,SCORE_METHOD!$B$37,SCORE_METHOD!$B$38) -> 1 | V11: =IF(data_CLEAN!V11<=SCORE_METHOD!$K$7,SCORE_METHOD!$N$6,IF(data_CLEAN!V11<=SCORE_METHOD!$K$8,SCORE_METHOD!$N$7,SCORE_METHOD!$N$8)) -> 3 | W11: =IF(data_CLEAN!W11<=SCORE_METHOD!$L$7,SCORE_METHOD!$N$6,IF(data_CLEAN!W11<=SCORE_METHOD!$L$8,SCORE_METHOD!$N$7,SCORE_METHOD!$N$8)) -> 3 | X11: =IF(data_CLEAN!X11<=SCORE_METHOD!$M$7,SCORE_METHOD!$N$6,IF(data_CLEAN!X11<=SCORE_METHOD!$M$8,SCORE_METHOD!$N$7,SCORE_METHOD!$N$8)) -> 1 | Y11: =VLOOKUP(data_CLEAN!Y11,SCORE_METHOD!$A$13:$F$15,6,FALSE) -> 1 | Z11: =SUM(C11:L11)*SCORE_METHOD!$E$53 -> 1.4 | AA11: =SUM(M11:N11)*SCORE_METHOD!$E$63 -> 2 | AB11: =SUM(O11:U11)*SCORE_METHOD!$E$65 -> 1.5714286 | AC11: =SUM(V11:Y11)*SCORE_METHOD!$E$72 -> 2 | AD11: =Z11*SCORE_METHOD!$C$44+data_SCORING!AA11*SCORE_METHOD!$C$45+data_SCORING!AB11*SCORE_METHOD!$C$46+data_SCORING!AC11*SCORE_METHOD!$C$47 -> 1.7428571
A12: FM1017-KG | B12: 76.142924 | C12: =IF(data_CLEAN!C12<=SCORE_METHOD!$B$7,SCORE_METHOD!$N$6,IF(data_CLEAN!C12<=SCORE_METHOD!$B$8,SCORE_METHOD!$N$7,SCORE_METHOD!$N$8)) -> 1 | D12: =IF(data_CLEAN!D12<=SCORE_METHOD!$C$7,SCORE_METHOD!$N$6,IF(data_CLEAN!D12<=SCORE_METHOD!$C$8,SCORE_METHOD!$N$7,SCORE_METHOD!$N$8)) -> 1 | E12: =IF(data_CLEAN!E12<=SCORE_METHOD!$D$7,SCORE_METHOD!$N$6,IF(data_CLEAN!E12<=SCORE_METHOD!$D$8,SCORE_METHOD!$N$7,SCORE_METHOD!$N$8)) -> 1 | F12: =IF(data_CLEAN!F12<=SCORE_METHOD!$E$7,SCORE_METHOD!$N$6,IF(data_CLEAN!F12<=SCORE_METHOD!$E$8,SCORE_METHOD!$N$7,SCORE_METHOD!$N$8)) -> 1 | G12: =IF(data_CLEAN!G12<=SCORE_METHOD!$F$7,SCORE_METHOD!$N$6,IF(data_CLEAN!G12<=SCORE_METHOD!$F$8,SCORE_METHOD!$N$7,SCORE_METHOD!$N$8)) -> 1 | H12: =VLOOKUP(data_CLEAN!H12,SCORE_METHOD!$A$13:$B$15,2,FALSE) -> 1 | I12: =VLOOKUP(data_CLEAN!I12,SCORE_METHOD!$A$13:$C$15,3,FALSE) -> 1 | J12: =VLOOKUP(data_CLEAN!J12,SCORE_METHOD!$A$13:$D$15,4,FALSE) -> 1 | K12: =VLOOKUP(data_CLEAN!K12,SCORE_METHOD!$A$13:$E$15,5,FALSE) -> 1 | L12: =VLOOKUP(data_CLEAN!L12,SCORE_METHOD!$A$19:$B$21,2,FALSE) -> 2 | M12: =IF(data_CLEAN!M12<=SCORE_METHOD!$G$7,SCORE_METHOD!$N$6,IF(data_CLEAN!M12<=SCORE_METHOD!$G$8,SCORE_METHOD!$N$7,SCORE_METHOD!$N$8)) -> 3 | N12: =IF(data_CLEAN!N12<=SCORE_METHOD!$H$7,SCORE_METHOD!$N$6,IF(data_CLEAN!N12<=SCORE_METHOD!$H$8,SCORE_METHOD!$N$7,SCORE_METHOD!$N$8)) -> 1 | O12: =VLOOKUP(data_CLEAN!O12,SCORE_METHOD!$A$25:$C$26,3,FALSE) -> 1 | P12: =IF(data_CLEAN!P12<=SCORE_METHOD!$I$7,SCORE_METHOD!$N$6,IF(data_CLEAN!P12<=SCORE_METHOD!$I$8,SCORE_METHOD!$N$7,SCORE_METHOD!$N$8)) -> 3 | Q12: =IF(data_CLEAN!Q12<=SCORE_METHOD!$B$31,SCORE_METHOD!$C$30,IF(data_CLEAN!Q12<=SCORE_METHOD!$B$32,SCORE_METHOD!$C$31,SCORE_METHOD!$C$32)) -> 1 | R12: =IF(data_CLEAN!R12<=SCORE_METHOD!$J$7,SCORE_METHOD!$N$6,IF(data_CLEAN!S12<=SCORE_METHOD!$J$8,SCORE_METHOD!$N$7,SCORE_METHOD!$N$8)) -> 2 | S12: =IF(data_CLEAN!S12<=SCORE_METHOD!$D$31,SCORE_METHOD!$E$30,IF(data_CLEAN!S12<=SCORE_METHOD!$D$32,SCORE_METHOD!$E$31,SCORE_METHOD!$E$32)) -> 3 | T12: =VLOOKUP(data_CLEAN!T12,SCORE_METHOD!$A$25:$E$26,5,FALSE) -> 0 | U12: =IF(data_CLEAN!U12=1,SCORE_METHOD!$B$37,SCORE_METHOD!$B$38) -> 1 | V12: =IF(data_CLEAN!V12<=SCORE_METHOD!$K$7,SCORE_METHOD!$N$6,IF(data_CLEAN!V12<=SCORE_METHOD!$K$8,SCORE_METHOD!$N$7,SCORE_METHOD!$N$8)) -> 3 | W12: =IF(data_CLEAN!W12<=SCORE_METHOD!$L$7,SCORE_METHOD!$N$6,IF(data_CLEAN!W12<=SCORE_METHOD!$L$8,SCORE_METHOD!$N$7,SCORE_METHOD!$N$8)) -> 2 | X12: =IF(data_CLEAN!X12<=SCORE_METHOD!$M$7,SCORE_METHOD!$N$6,IF(data_CLEAN!X12<=SCORE_METHOD!$M$8,SCORE_METHOD!$N$7,SCORE_METHOD!$N$8)) -> 2 | Y12: =VLOOKUP(data_CLEAN!Y12,SCORE_METHOD!$A$13:$F$15,6,FALSE) -> 2 | Z12: =SUM(C12:L12)*SCORE_METHOD!$E$53 -> 1.1 | AA12: =SUM(M12:N12)*SCORE_METHOD!$E$63 -> 2 | AB12: =SUM(O12:U12)*SCORE_METHOD!$E$65 -> 1.5714286 | AC12: =SUM(V12:Y12)*SCORE_METHOD!$E$72 -> 2.25 | AD12: =Z12*SCORE_METHOD!$C$44+data_SCORING!AA12*SCORE_METHOD!$C$45+data_SCORING!AB12*SCORE_METHOD!$C$46+data_SCORING!AC12*SCORE_METHOD!$C$47 -> 1.7303571
A13: FM1021-KG | B13: 41.656805 | C13: =IF(data_CLEAN!C13<=SCORE_METHOD!$B$7,SCORE_METHOD!$N$6,IF(data_CLEAN!C13<=SCORE_METHOD!$B$8,SCORE_METHOD!$N$7,SCORE_METHOD!$N$8)) -> 3 | D13: =IF(data_CLEAN!D13<=SCORE_METHOD!$C$7,SCORE_METHOD!$N$6,IF(data_CLEAN!D13<=SCORE_METHOD!$C$8,SCORE_METHOD!$N$7,SCORE_METHOD!$N$8)) -> 3 | E13: =IF(data_CLEAN!E13<=SCORE_METHOD!$D$7,SCORE_METHOD!$N$6,IF(data_CLEAN!E13<=SCORE_METHOD!$D$8,SCORE_METHOD!$N$7,SCORE_METHOD!$N$8)) -> 1 | F13: =IF(data_CLEAN!F13<=SCORE_METHOD!$E$7,SCORE_METHOD!$N$6,IF(data_CLEAN!F13<=SCORE_METHOD!$E$8,SCORE_METHOD!$N$7,SCORE_METHOD!$N$8)) -> 1 | G13: =IF(data_CLEAN!G13<=SCORE_METHOD!$F$7,SCORE_METHOD!$N$6,IF(data_CLEAN!G13<=SCORE_METHOD!$F$8,SCORE_METHOD!$N$7,SCORE_METHOD!$N$8)) -> 1 | H13: =VLOOKUP(data_CLEAN!H13,SCORE_METHOD!$A$13:$B$15,2,FALSE) -> 1 | I13: =VLOOKUP(data_CLEAN!I13,SCORE_METHOD!$A$13:$C$15,3,FALSE) -> 3 | J13: =VLOOKUP(data_CLEAN!J13,SCORE_METHOD!$A$13:$D$15,4,FALSE) -> 1 | K13: =VLOOKUP(data_CLEAN!K13,SCORE_METHOD!$A$13:$E$15,5,FALSE) -> 3 | L13: =VLOOKUP(data_CLEAN!L13,SCORE_METHOD!$A$19:$B$21,2,FALSE) -> 3 | M13: =IF(data_CLEAN!M13<=SCORE_METHOD!$G$7,SCORE_METHOD!$N$6,IF(data_CLEAN!M13<=SCORE_METHOD!$G$8,SCORE_METHOD!$N$7,SCORE_METHOD!$N$8)) -> 1 | N13: =IF(data_CLEAN!N13<=SCORE_METHOD!$H$7,SCORE_METHOD!$N$6,IF(data_CLEAN!N13<=SCORE_METHOD!$H$8,SCORE_METHOD!$N$7,SCORE_METHOD!$N$8)) -> 1 | O13: =VLOOKUP(data_CLEAN!O13,SCORE_METHOD!$A$25:$C$26,3,FALSE) -> 1 | P13: =IF(data_CLEAN!P13<=SCORE_METHOD!$I$7,SCORE_METHOD!$N$6,IF(data_CLEAN!P13<=SCORE_METHOD!$I$8,SCORE_METHOD!$N$7,SCORE_METHOD!$N$8)) -> 2 | Q13: =IF(data_CLEAN!Q13<=SCORE_METHOD!$B$31,SCORE_METHOD!$C$30,IF(data_CLEAN!Q13<=SCORE_METHOD!$B$32,SCORE_METHOD!$C$31,SCORE_METHOD!$C$32)) -> 3 | R13: =IF(data_CLEAN!R13<=SCORE_METHOD!$J$7,SCORE_METHOD!$N$6,IF(data_CLEAN!S13<=SCORE_METHOD!$J$8,SCORE_METHOD!$N$7,SCORE_METHOD!$N$8)) -> 3 | S13: =IF(data_CLEAN!S13<=SCORE_METHOD!$D$31,SCORE_METHOD!$E$30,IF(data_CLEAN!S13<=SCORE_METHOD!$D$32,SCORE_METHOD!$E$31,SCORE_METHOD!$E$32)) -> 1 | T13: =VLOOKUP(data_CLEAN!T13,SCORE_METHOD!$A$25:$E$26,5,FALSE) -> 0 | U13: =IF(data_CLEAN!U13=1,SCORE_METHOD!$B$37,SCORE_METHOD!$B$38) -> 1 | V13: =IF(data_CLEAN!V13<=SCORE_METHOD!$K$7,SCORE_METHOD!$N$6,IF(data_CLEAN!V13<=SCORE_METHOD!$K$8,SCORE_METHOD!$N$7,SCORE_METHOD!$N$8)) -> 1 | W13: =IF(data_CLEAN!W13<=SCORE_METHOD!$L$7,SCORE_METHOD!$N$6,IF(data_CLEAN!W13<=SCORE_METHOD!$L$8,SCORE_METHOD!$N$7,SCORE_METHOD!$N$8)) -> 2 | X13: =IF(data_CLEAN!X13<=SCORE_METHOD!$M$7,SCORE_METHOD!$N$6,IF(data_CLEAN!X13<=SCORE_METHOD!$M$8,SCORE_METHOD!$N$7,SCORE_METHOD!$N$8)) -> 1 | Y13: =VLOOKUP(data_CLEAN!Y13,SCORE_METHOD!$A$13:$F$15,6,FALSE) -> 2 | Z13: =SUM(C13:L13)*SCORE_METHOD!$E$53 -> 2 | AA13: =SUM(M13:N13)*SCORE_METHOD!$E$63 -> 1 | AB13: =SUM(O13:U13)*SCORE_METHOD!$E$65 -> 1.5714286 | AC13: =SUM(V13:Y13)*SCORE_METHOD!$E$72 -> 1.5 | AD13: =Z13*SCORE_METHOD!$C$44+data_SCORING!AA13*SCORE_METHOD!$C$45+data_SCORING!AB13*SCORE_METHOD!$C$46+data_SCORING!AC13*SCORE_METHOD!$C$47 -> 1.5178571
A14: FM1023-KG | B14: 18.352813 | C14: =IF(data_CLEAN!C14<=SCORE_METHOD!$B$7,SCORE_METHOD!$N$6,IF(data_CLEAN!C14<=SCORE_METHOD!$B$8,SCORE_METHOD!$N$7,SCORE_METHOD!$N$8)) -> 2 | D14: =IF(data_CLEAN!D14<=SCORE_METHOD!$C$7,SCORE_METHOD!$N$6,IF(data_CLEAN!D14<=SCORE_METHOD!$C$8,SCORE_METHOD!$N$7,SCORE_METHOD!$N$8)) -> 1 | E14: =IF(data_CLEAN!E14<=SCORE_METHOD!$D$7,SCORE_METHOD!$N$6,IF(data_CLEAN!E14<=SCORE_METHOD!$D$8,SCORE_METHOD!$N$7,SCORE_METHOD!$N$8)) -> 1 | F14: =IF(data_CLEAN!F14<=SCORE_METHOD!$E$7,SCORE_METHOD!$N$6,IF(data_CLEAN!F14<=SCORE_METHOD!$E$8,SCORE_METHOD!$N$7,SCORE_METHOD!$N$8)) -> 3 | G14: =IF(data_CLEAN!G14<=SCORE_METHOD!$F$7,SCORE_METHOD!$N$6,IF(data_CLEAN!G14<=SCORE_METHOD!$F$8,SCORE_METHOD!$N$7,SCORE_METHOD!$N$8)) -> 1 | H14: =VLOOKUP(data_CLEAN!H14,SCORE_METHOD!$A$13:$B$15,2,FALSE) -> 1 | I14: =VLOOKUP(data_CLEAN!I14,SCORE_METHOD!$A$13:$C$15,3,FALSE) -> 3 | J14: =VLOOKUP(data_CLEAN!J14,SCORE_METHOD!$A$13:$D$15,4,FALSE) -> 1 | K14: =VLOOKUP(data_CLEAN!K14,SCORE_METHOD!$A$13:$E$15,5,FALSE) -> 3 | L14: =VLOOKUP(data_CLEAN!L14,SCORE_METHOD!$A$19:$B$21,2,FALSE) -> 1 | M14: =IF(data_CLEAN!M14<=SCORE_METHOD!$G$7,SCORE_METHOD!$N$6,IF(data_CLEAN!M14<=SCORE_METHOD!$G$8,SCORE_METHOD!$N$7,SCORE_METHOD!$N$8)) -> 1 | N14: =IF(data_CLEAN!N14<=SCORE_METHOD!$H$7,SCORE_METHOD!$N$6,IF(data_CLEAN!N14<=SCORE_METHOD!$H$8,SCORE_METHOD!$N$7,SCORE_METHOD!$N$8)) -> 1 | O14: =VLOOKUP(data_CLEAN!O14,SCORE_METHOD!$A$25:$C$26,3,FALSE) -> 1 | P14: =IF(data_CLEAN!P14<=SCORE_METHOD!$I$7,SCORE_METHOD!$N$6,IF(data_CLEAN!P14<=SCORE_METHOD!$I$8,SCORE_METHOD!$N$7,SCORE_METHOD!$N$8)) -> 2 | Q14: =IF(data_CLEAN!Q14<=SCORE_METHOD!$B$31,SCORE_METHOD!$C$30,IF(data_CLEAN!Q14<=SCORE_METHOD!$B$32,SCORE_METHOD!$C$31,SCORE_METHOD!$C$32)) -> 3 | R14: =IF(data_CLEAN!R14<=SCORE_METHOD!$J$7,SCORE_METHOD!$N$6,IF(data_CLEAN!S14<=SCORE_METHOD!$J$8,SCORE_METHOD!$N$7,SCORE_METHOD!$N$8)) -> 1 | S14: =IF(data_CLEAN!S14<=SCORE_METHOD!$D$31,SCORE_METHOD!$E$30,IF(data_CLEAN!S14<=SCORE_METHOD!$D$32,SCORE_METHOD!$E$31,SCORE_METHOD!$E$32)) -> 3 | T14: =VLOOKUP(data_CLEAN!T14,SCORE_METHOD!$A$25:$E$26,5,FALSE) -> 0 | U14: =IF(data_CLEAN!U14=1,SCORE_METHOD!$B$37,SCORE_METHOD!$B$38) -> 1 | V14: =IF(data_CLEAN!V14<=SCORE_METHOD!$K$7,SCORE_METHOD!$N$6,IF(data_CLEAN!V14<=SCORE_METHOD!$K$8,SCORE_METHOD!$N$7,SCORE_METHOD!$N$8)) -> 2 | W14: =IF(data_CLEAN!W14<=SCORE_METHOD!$L$7,SCORE_METHOD!$N$6,IF(data_CLEAN!W14<=SCORE_METHOD!$L$8,SCORE_METHOD!$N$7,SCORE_METHOD!$N$8)) -> 2 | X14: =IF(data_CLEAN!X14<=SCORE_METHOD!$M$7,SCORE_METHOD!$N$6,IF(data_CLEAN!X14<=SCORE_METHOD!$M$8,SCORE_METHOD!$N$7,SCORE_METHOD!$N$8)) -> 2 | Y14: =VLOOKUP(data_CLEAN!Y14,SCORE_METHOD!$A$13:$F$15,6,FALSE) -> 3 | Z14: =SUM(C14:L14)*SCORE_METHOD!$E$53 -> 1.7 | AA14: =SUM(M14:N14)*SCORE_METHOD!$E$63 -> 1 | AB14: =SUM(O14:U14)*SCORE_METHOD!$E$65 -> 1.5714286 | AC14: =SUM(V14:Y14)*SCORE_METHOD!$E$72 -> 2.25 | AD14: =Z14*SCORE_METHOD!$C$44+data_SCORING!AA14*SCORE_METHOD!$C$45+data_SCORING!AB14*SCORE_METHOD!$C$46+data_SCORING!AC14*SCORE_METHOD!$C$47 -> 1.6303571
... A58: US0385-KG | B58: 97.141263 | C58: =IF(data_CLEAN!C58<=SCORE_METHOD!$B$7,SCORE_METHOD!$N$6,IF(data_CLEAN!C58<=SCORE_METHOD!$B$8,SCORE_METHOD!$N$7,SCORE_METHOD!$N$8)) -> 2 | D58: =IF(data_CLEAN!D58<=SCORE_METHOD!$C$7,SCORE_METHOD!$N$6,IF(data_CLEAN!D58<=SCORE_METHOD!$C$8,SCORE_METHOD!$N$7,SCORE_METHOD!$N$8)) -> 3 | E58: =IF(data_CLEAN!E58<=SCORE_METHOD!$D$7,SCORE_METHOD!$N$6,IF(data_CLEAN!E58<=SCORE_METHOD!$D$8,SCORE_METHOD!$N$7,SCORE_METHOD!$N$8)) -> 3 | F58: =IF(data_CLEAN!F58<=SCORE_METHOD!$E$7,SCORE_METHOD!$N$6,IF(data_CLEAN!F58<=SCORE_METHOD!$E$8,SCORE_METHOD!$N$7,SCORE_METHOD!$N$8)) -> 3 | G58: =IF(data_CLEAN!G58<=SCORE_METHOD!$F$7,SCORE_METHOD!$N$6,IF(data_CLEAN!G58<=SCORE_METHOD!$F$8,SCORE_METHOD!$N$7,SCORE_METHOD!$N$8)) -> 3 | H58: =VLOOKUP(data_CLEAN!H58,SCORE_METHOD!$A$13:$B$15,2,FALSE) -> 3 | I58: =VLOOKUP(data_CLEAN!I58,SCORE_METHOD!$A$13:$C$15,3,FALSE) -> 3 | J58: =VLOOKUP(data_CLEAN!J58,SCORE_METHOD!$A$13:$D$15,4,FALSE) -> 3 | K58: =VLOOKUP(data_CLEAN!K58,SCORE_METHOD!$A$13:$E$15,5,FALSE) -> 3 | L58: =VLOOKUP(data_CLEAN!L58,SCORE_METHOD!$A$19:$B$21,2,FALSE) -> 2 | M58: =IF(data_CLEAN!M58<=SCORE_METHOD!$G$7,SCORE_METHOD!$N$6,IF(data_CLEAN!M58<=SCORE_METHOD!$G$8,SCORE_METHOD!$N$7,SCORE_METHOD!$N$8)) -> 2 | N58: =IF(data_CLEAN!N58<=SCORE_METHOD!$H$7,SCORE_METHOD!$N$6,IF(data_CLEAN!N58<=SCORE_METHOD!$H$8,SCORE_METHOD!$N$7,SCORE_METHOD!$N$8)) -> 3 | O58: =VLOOKUP(data_CLEAN!O58,SCORE_METHOD!$A$25:$C$26,3,FALSE) -> 1 | P58: =IF(data_CLEAN!P58<=SCORE_METHOD!$I$7,SCORE_METHOD!$N$6,IF(data_CLEAN!P58<=SCORE_METHOD!$I$8,SCORE_METHOD!$N$7,SCORE_METHOD!$N$8)) -> 1 | Q58: =IF(data_CLEAN!Q58<=SCORE_METHOD!$B$31,SCORE_METHOD!$C$30,IF(data_CLEAN!Q58<=SCORE_METHOD!$B$32,SCORE_METHOD!$C$31,SCORE_METHOD!$C$32)) -> 1 | R58: =IF(data_CLEAN!R58<=SCORE_METHOD!$J$7,SCORE_METHOD!$N$6,IF(data_CLEAN!S58<=SCORE_METHOD!$J$8,SCORE_METHOD!$N$7,SCORE_METHOD!$N$8)) -> 2 | S58: =IF(data_CLEAN!S58<=SCORE_METHOD!$D$31,SCORE_METHOD!$E$30,IF(data_CLEAN!S58<=SCORE_METHOD!$D$32,SCORE_METHOD!$E$31,SCORE_METHOD!$E$32)) -> 3 | T58: =VLOOKUP(data_CLEAN!T58,SCORE_METHOD!$A$25:$E$26,5,FALSE) -> 0 | U58: =IF(data_CLEAN!U58=1,SCORE_METHOD!$B$37,SCORE_METHOD!$B$38) -> 1 | V58: =IF(data_CLEAN!V58<=SCORE_METHOD!$K$7,SCORE_METHOD!$N$6,IF(data_CLEAN!V58<=SCORE_METHOD!$K$8,SCORE_METHOD!$N$7,SCORE_METHOD!$N$8)) -> 1 | W58: =IF(data_CLEAN!W58<=SCORE_METHOD!$L$7,SCORE_METHOD!$N$6,IF(data_CLEAN!W58<=SCORE_METHOD!$L$8,SCORE_METHOD!$N$7,SCORE_METHOD!$N$8)) -> 2 | X58: =IF(data_CLEAN!X58<=SCORE_METHOD!$M$7,SCORE_METHOD!$N$6,IF(data_CLEAN!X58<=SCORE_METHOD!$M$8,SCORE_METHOD!$N$7,SCORE_METHOD!$N$8)) -> 2 | Y58: =VLOOKUP(data_CLEAN!Y58,SCORE_METHOD!$A$13:$F$15,6,FALSE) -> 2 | Z58: =SUM(C58:L58)*SCORE_METHOD!$E$53 -> 2.8 | AA58: =SUM(M58:N58)*SCORE_METHOD!$E$63 -> 2.5 | AB58: =SUM(O58:U58)*SCORE_METHOD!$E$65 -> 1.2857143 | AC58: =SUM(V58:Y58)*SCORE_METHOD!$E$72 -> 1.75 | AD58: =Z58*SCORE_METHOD!$C$44+data_SCORING!AA58*SCORE_METHOD!$C$45+data_SCORING!AB58*SCORE_METHOD!$C$46+data_SCORING!AC58*SCORE_METHOD!$C$47 -> 2.0839286

Sheet data_MAPPING
A1: Corridor_j | B1: Miles | C1: mob_rel_con_score | D1: safe_sec_score | E1: asst_pres_tech_score | F1: cust_stew_sust_eq_score | G1: final_score | H1: region | I1: Mark_Access_score | J1: Pe_G_M_score | K1: Net_Desg_score | L1: Needs_Cat | M1: ND_Cat | N1: Corridor
A2: SH0349-KG | B2: 95.026899 | C2: 1.6 | D2: 1 | E2: 1.4285714 | F2: 1.25 | G2: 1.3196429 | H2: West | I2: 3.147276 | J2: 2.4124289 | K2: 5.6481794 | L2: =IF(G2<=SCORE_METHOD!$B$116,"Low",IF(data_MAPPING!G2<=SCORE_METHOD!$C$116,"Medium","High")) -> Low | M2: =IF(K2<=SCORE_METHOD!$B$112,"Low",IF(data_MAPPING!K2<=SCORE_METHOD!$C$112,"Medium","High")) -> Low | N2: SH 349
A3: FM2644-KG | B3: 26.949391 | C3: 1.8 | D3: 1 | E3: 1.7142857 | F3: 1.25 | G3: 1.4410714 | H3: Central | I3: 3.7234378 | J3: 2.6507948 | K3: 6.2952041 | L3: =IF(G3<=SCORE_METHOD!$B$116,"Low",IF(data_MAPPING!G3<=SCORE_METHOD!$C$116,"Medium","High")) -> Low | M3: =IF(K3<=SCORE_METHOD!$B$112,"Low",IF(data_MAPPING!K3<=SCORE_METHOD!$C$112,"Medium","High")) -> Low | N3: FM 2644
A4: SH0359-2 | B4: 42.901241 | C4: 1.8 | D4: 1.5 | E4: 1.4285714 | F4: 2 | G4: 1.6821429 | H4: South | I4: 3.4583333 | J4: 2.7111111 | K4: 6.0694444 | L4: =IF(G4<=SCORE_METHOD!$B$116,"Low",IF(data_MAPPING!G4<=SCORE_METHOD!$C$116,"Medium","High")) -> Medium | M4: =IF(K4<=SCORE_METHOD!$B$112,"Low",IF(data_MAPPING!K4<=SCORE_METHOD!$C$112,"Medium","High")) -> Low | N4: SH 359 (Jim Hogg to Duval County)
A5: RM1111-KG | B5: 42.291837 | C5: 1.4 | D5: 1 | E5: 1.7142857 | F5: 2 | G5: 1.5285714 | H5: West | I5: 2.8444313 | J5: 2.7461905 | K5: 5.6088889 | L5: =IF(G5<=SCORE_METHOD!$B$116,"Low",IF(data_MAPPING!G5<=SCORE_METHOD!$C$116,"Medium","High")) -> Low | M5: =IF(K5<=SCORE_METHOD!$B$112,"Low",IF(data_MAPPING!K5<=SCORE_METHOD!$C$112,"Medium","High")) -> Low | N5: RM 1111
A6: FM0650-KG | B6: 3.4067871 | C6: 1.6 | D6: 2 | E6: 1.4285714 | F6: 1.25 | G6: 1.5696429 | H6: South | I6: 3.3333333 | J6: 2.9777778 | K6: 6.3111111 | L6: =IF(G6<=SCORE_METHOD!$B$116,"Low",IF(data_MAPPING!G6<=SCORE_METHOD!$C$116,"Medium","High")) -> Low | M6: =IF(K6<=SCORE_METHOD!$B$112,"Low",IF(data_MAPPING!K6<=SCORE_METHOD!$C$112,"Medium","High")) -> Low | N6: FM 650
A7: US0190-KG | B7: 122.66597 | C7: 2.4 | D7: 2 | E7: 1.4285714 | F7: 1.75 | G7: 1.8946429 | H7: Central | I7: 3.124026 | J7: 3.3897326 | K7: 6.6226642 | L7: =IF(G7<=SCORE_METHOD!$B$116,"Low",IF(data_MAPPING!G7<=SCORE_METHOD!$C$116,"Medium","High")) -> High | M7: =IF(K7<=SCORE_METHOD!$B$112,"Low",IF(data_MAPPING!K7<=SCORE_METHOD!$C$112,"Medium","High")) -> Low | N7: US 190
A8: FM2369-KG | B8: 4.2164203 | C8: 1.8 | D8: 1.5 | E8: 1.7142857 | F8: 2 | G8: 1.7535714 | H8: Central | I8: 5.2733512 | J8: 3.420863 | K8: 8.6711979 | L8: =IF(G8<=SCORE_METHOD!$B$116,"Low",IF(data_MAPPING!G8<=SCORE_METHOD!$C$116,"Medium","High")) -> Medium | M8: =IF(K8<=SCORE_METHOD!$B$112,"Low",IF(data_MAPPING!K8<=SCORE_METHOD!$C$112,"Medium","High")) -> Medium | N8: FM 2369
A9: US0090-2 | B9: 195.19672 | C9: 2 | D9: 3 | E9: 1.4285714 | F9: 2.25 | G9: 2.1696429 | H9: West | I9: 3.5075019 | J9: 3.6399 | K9: 7.2092771 | L9: =IF(G9<=SCORE_METHOD!$B$116,"Low",IF(data_MAPPING!G9<=SCORE_METHOD!$C$116,"Medium","High")) -> High | M9: =IF(K9<=SCORE_METHOD!$B$112,"Low",IF(data_MAPPING!K9<=SCORE_METHOD!$C$112,"Medium","High")) -> Low | N9: US 90 (Terrell to Culberson County)
A10: SH0017-KG | B10: 90.816484 | C10: 2 | D10: 1.5 | E10: 1.2857143 | F10: 2.5 | G10: 1.8214286 | H10: West | I10: 3.8360054 | J10: 3.7339468 | K10: 7.6135461 | L10: =IF(G10<=SCORE_METHOD!$B$116,"Low",IF(data_MAPPING!G10<=SCORE_METHOD!$C$116,"Medium","High")) -> Medium | M10: =IF(K10<=SCORE_METHOD!$B$112,"Low",IF(data_MAPPING!K10<=SCORE_METHOD!$C$112,"Medium","High")) -> Low | N10: SH 17
A11: US0062-KG | B11: 114.62001 | C11: 2.2 | D11: 3 | E11: 0.85714286 | F11: 2.75 | G11: 2.2017857 | H11: West | I11: 4.4517731 | J11: 3.7645071 | K11: 8.2690787 | L11: =IF(G11<=SCORE_METHOD!$B$116,"Low",IF(data_MAPPING!G11<=SCORE_METHOD!$C$116,"Medium","High")) -> High | M11: =IF(K11<=SCORE_METHOD!$B$112,"Low",IF(data_MAPPING!K11<=SCORE_METHOD!$C$112,"Medium","High")) -> Low | N11: US 62
A12: FM1023-KG | B12: 18.352813 | C12: 1.7 | D12: 1 | E12: 1.5714286 | F12: 2.25 | G12: 1.6303571 | H12: Central | I12: 4.832745 | J12: 3.7726196 | K12: 8.7328848 | L12: =IF(G12<=SCORE_METHOD!$B$116,"Low",IF(data_MAPPING!G12<=SCORE_METHOD!$C$116,"Medium","High")) -> Low | M12: =IF(K12<=SCORE_METHOD!$B$112,"Low",IF(data_MAPPING!K12<=SCORE_METHOD!$C$112,"Medium","High")) -> Medium | N12: FM 1023
A13: FM1015-KG | B13: 20.004862 | C13: 1.4 | D13: 2 | E13: 1.5714286 | F13: 2 | G13: 1.7428571 | H13: South | I13: 4.5423863 | J13: 3.817664 | K13: 8.315607 | L13: =IF(G13<=SCORE_METHOD!$B$116,"Low",IF(data_MAPPING!G13<=SCORE_METHOD!$C$116,"Medium","High")) -> Medium | M13: =IF(K13<=SCORE_METHOD!$B$112,"Low",IF(data_MAPPING!K13<=SCORE_METHOD!$C$112,"Medium","High")) -> Low | N13: FM 1015
... A54: US0083-2 | B54: 32.809901 | C54: 2.3 | D54: 1.5 | E54: 1.1428571 | F54: 1 | G54: 1.4857143 | H54: Central | I54: 5.5299951 | J54: 6.5746 | K54: 12.113884 | L54: =IF(G54<=SCORE_METHOD!$B$116,"Low",IF(data_MAPPING!G54<=SCORE_METHOD!$C$116,"Medium","High")) -> Low | M54: =IF(K54<=SCORE_METHOD!$B$112,"Low",IF(data_MAPPING!K54<=SCORE_METHOD!$C$112,"Medium","High")) -> High | N54: US 83 (Webb County)
A55: SL0480-F | B55: 6.5691874 | C55: 1.2 | D55: 2 | E55: 1.4285714 | F55: 1.5 | G55: 1.5321429 | H55: Central | I55: #N/A | J55: #N/A | K55: #N/A | L55: =IF(G55<=SCORE_METHOD!$B$116,"Low",IF(data_MAPPING!G55<=SCORE_METHOD!$C$116,"Medium","High")) -> Low | M55: =IF(K55<=SCORE_METHOD!$B$112,"Low",IF(data_MAPPING!K55<=SCORE_METHOD!$C$112,"Medium","High")) -> #N/A | N55: SL 480 (N Eagle Pass)
A56: SL0195-F | B56: 16.030752 | C56: 1.4 | D56: 1.5 | E56: 1.4285714 | F56: 1.75 | G56: 1.5196429 | H56: South | I56: #N/A | J56: #N/A | K56: #N/A | L56: =IF(G56<=SCORE_METHOD!$B$116,"Low",IF(data_MAPPING!G56<=SCORE_METHOD!$C$116,"Medium","High")) -> Low | M56: =IF(K56<=SCORE_METHOD!$B$112,"Low",IF(data_MAPPING!K56<=SCORE_METHOD!$C$112,"Medium","High")) -> #N/A | N56: SL 195
A57: 240AA1005 | B57: 12.562325 | C57: 1.6 | D57: 1 | E57: 1.4285714 | F57: 1 | G57: 1.2571429 | H57: South | I57: #N/A | J57: #N/A | K57: #N/A | L57: =IF(G57<=SCORE_METHOD!$B$116,"Low",IF(data_MAPPING!G57<=SCORE_METHOD!$C$116,"Medium","High")) -> Low | M57: =IF(K57<=SCORE_METHOD!$B$112,"Low",IF(data_MAPPING!K57<=SCORE_METHOD!$C$112,"Medium","High")) -> #N/A | N57: 240AA1005 (Webb County)

Sheet report
B1: Top 10 Corridors by Needs Score
A5: Corridor_excel | B5: Rank | C5: Corridor | D5: Miles | E5: Mobility, Reliability, and Connectivity | F5: Safety and Security | G5: Asset Preservation and Technology | H5: Customer Service and Stewardship | I5: Final Needs Score | J5: Region
A6: SH 173 (part 2) | B6: 5 | C6: US 57 | D6: 98 | E6: 2.3 | F6: 2.5 | G6: 1.29 | H6: 2.75 | I6: 2.21 | J6: Central
A7: US 83 (part 1) | B7: 1 | C7: US 83 (Kimble to Dimmit County) | D7: 191 | E7: 2.5 | F7: 3 | G7: 1 | H7: 2.75 | I7: 2.31 | J7: Central
A8: US 83 (part 3) | B8: 3 | C8: US 90 (Medina to Val Verde County) | D8: 207 | E8: 2.3 | F8: 3 | G8: 1 | H8: 2.75 | I8: 2.26 | J8: Central
A9: US 90 (part 1) | B9: 6 | C9: US 62 | D9: 115 | E9: 2.2 | F9: 3 | G9: 0.86 | H9: 2.75 | I9: 2.2 | J9: West
A10: US 385 | B10: 2 | C10: SH 173 (Kerr to Frio County) | D10: 84 | E10: 2.3 | F10: 3 | G10: 1.43 | H10: 2.5 | I10: 2.31 | J10: Central
A11: US 90 (part 2) | B11: 9 | C11: US 285 | D11: 170 | E11: 2 | F11: 3 | G11: 1.14 | H11: 2.5 | I11: 2.16 | J11: West
A12: SH 44 (part 2) | B12: 4 | C12: US 83 (Starr to Webb County) | D12: 108 | E12: 2.8 | F12: 2.5 | G12: 1.14 | H12: 2.5 | I12: 2.24 | J12: South
A13: US 57 | B13: 7 | C13: US 90 (Terrell to Culberson County) | D13: 195 | E13: 2 | F13: 3 | G13: 1.43 | H13: 2.25 | I13: 2.17 | J13: West
A14: US 62 | B14: 8 | C14: SH 44 (Jim Wells to Duval County) | D14: 43 | E14: 2.4 | F14: 3 | G14: 1 | H14: 2.25 | I14: 2.16 | J14: South
A15: US 285 | B15: 10 | C15: US 385 | D15: 97 | E15: 2.8 | F15: 2.5 | G15: 1.29 | H15: 1.75 | I15: 2.08 | J15: West
C21: Needs Assessment | H21: Network Designation | K21: Corridor Needs | L21: Corridor Importance | M21: Region
A22: Corridor | B22: Miles | C22: Mobility, Reliability, & Connectivity | D22: Safety & Security | E22: Asset Preservation and Technology Deployment | F22: Customer Service, Stewardship and Sustainability, and Equity | G22: Final Needs Score | H22: Market Access | I22: People and Goods Movement | J22: Network Designation Score
A23: SH0349-KG | B23: 95.026899 | C23: 1.6 | D23: 1 | E23: 1.4285714 | F23: 1.25 | G23: 1.3196429 | H23: 3.147276 | I23: 2.4124289 | J23: 5.6481794 | K23: Low | L23: Low | M23: west
A24: FM2644-KG | B24: 26.949391 | C24: 1.8 | D24: 1 | E24: 1.7142857 | F24: 1.25 | G24: 1.4410714 | H24: 3.7234378 | I24: 2.6507948 | J24: 6.2952041 | K24: Low | L24: Low | M24: central
A25: SH0359-2 | B25: 42.901241 | C25: 1.8 | D25: 1.5 | E25: 1.4285714 | F25: 2 | G25: 1.6821429 | H25: 3.4583333 | I25: 2.7111111 | J25: 6.0694444 | K25: Medium | L25: Low | M25: south
A26: RM1111-KG | B26: 42.291837 | C26: 1.4 | D26: 1 | E26: 1.7142857 | F26: 2 | G26: 1.5285714 | H26: 2.8444313 | I26: 2.7461905 | J26: 5.6088889 | K26: Low | L26: Low | M26: west
A27: FM0650-KG | B27: 3.4067871 | C27: 1.6 | D27: 2 | E27: 1.4285714 | F27: 1.25 | G27: 1.5696429 | H27: 3.3333333 | I27: 2.9777778 | J27: 6.3111111 | K27: Low | L27: Low | M27: south
A28: US0190-KG | B28: 122.66597 | C28: 2.4 | D28: 2 | E28: 1.4285714 | F28: 1.75 | G28: 1.8946429 | H28: 3.124026 | I28: 3.3897326 | J28: 6.6226642 | K28: High | L28: Low | M28: central
A29: FM2369-KG | B29: 4.2164203 | C29: 1.8 | D29: 1.5 | E29: 1.7142857 | F29: 2 | G29: 1.7535714 | H29: 5.2733512 | I29: 3.420863 | J29: 8.6711979 | K29: Medium | L29: Medium | M29: central
A30: US0090-2 | B30: 195.19672 | C30: 2 | D30: 3 | E30: 1.4285714 | F30: 2.25 | G30: 2.1696429 | H30: 3.5075019 | I30: 3.6399 | J30: 7.2092771 | K30: High | L30: Low | M30: west
A31: SH0017-KG | B31: 90.816484 | C31: 2 | D31: 1.5 | E31: 1.2857143 | F31: 2.5 | G31: 1.8214286 | H31: 3.8360054 | I31: 3.7339468 | J31: 7.6135461 | K31: Medium | L31: Low | M31: west
A32: US0062-KG | B32: 114.62001 | C32: 2.2 | D32: 3 | E32: 0.85714286 | F32: 2.75 | G32: 2.2017857 | H32: 4.4517731 | I32: 3.7645071 | J32: 8.2690787 | K32: High | L32: Low | M32: west
A33: FM1023-KG | B33: 18.352813 | C33: 1.7 | D33: 1 | E33: 1.5714286 | F33: 2.25 | G33: 1.6303571 | H33: 4.832745 | I33: 3.7726196 | J33: 8.7328848 | K33: Low | L33: Medium | M33: central
A34: FM1015-KG | B34: 20.004862 | C34: 1.4 | D34: 2 | E34: 1.5714286 | F34: 2 | G34: 1.7428571 | H34: 4.5423863 | I34: 3.817664 | J34: 8.315607 | K34: Medium | L34: Low | M34: south
... A75: US0083-2 | B75: 32.809901 | C75: 2.3 | D75: 1.5 | E75: 1.1428571 | F75: 1 | G75: 1.4857143 | H75: 5.5299951 | I75: 6.5746 | J75: 12.113884 | K75: Low | L75: High | M75: central
A76: SL0480-F | B76: 6.5691874 | C76: 1.2 | D76: 2 | E76: 1.4285714 | F76: 1.5 | G76: 1.5321429 | H76: No Data | I76: No Data | J76: No Data | K76: Low | L76: No Data | M76: central
A77: SL0195-F | B77: 16.030752 | C77: 1.4 | D77: 1.5 | E77: 1.4285714 | F77: 1.75 | G77: 1.5196429 | H77: No Data | I77: No Data | J77: No Data | K77: Low | L77: No Data | M77: south
A78: 240AA1005 | B78: 12.562325 | C78: 1.6 | D78: 1 | E78: 1.4285714 | F78: 1 | G78: 1.2571429 | H78: No Data | I78: No Data | J78: No Data | K78: Low | L78: No Data | M78: south

Sheet SCORE_METHOD
A2: Metric scores
A5: The higher the value, the bigger the need | B5: existing vc | C5: forecasted vc | D5: TTRI | E5: delay_psgr_s_corr | F5: delay_trk_s_corr | G5: Safety | H5: RR_crash | I5: % lane mileage with 2 or less lanes | J5: Pavement Conditions | K5: access to historic, cultural, and tourist activities | L5: EV charging inventory and proximity | M5: access to rest areas/truck parking | N5: Metric Need
B6: Lower than below | C6: Lower than below | D6: Lower than below | E6: Lower than below | F6: Lower than below | G6: Lower than below | H6: Lower than below | I6: Lower than below | J6: Lower than below | K6: Lower than below | L6: Lower than below | M6: Lower than below | N6: 1
A7: 33%tile | B7: =_xlfn.PERCENTILE.INC(data_CLEAN!$C$3:$C$58,1/3) -> 0.029389746 | C7: =_xlfn.PERCENTILE.INC(data_CLEAN!D$3:D$58,1/3) -> 0.031618784 | D7: =_xlfn.PERCENTILE.INC(data_CLEAN!E$3:E$58,1/3) -> 0 | E7: =_xlfn.PERCENTILE.INC(data_CLEAN!F$3:F$58,1/3) -> 0 | F7: =_xlfn.PERCENTILE.INC(data_CLEAN!G$3:G$58,1/3) -> 0 | G7: =_xlfn.PERCENTILE.INC(data_CLEAN!M$3:M$58,1/3) -> 5593.6441 | H7: =_xlfn.PERCENTILE.INC(data_CLEAN!N$3:N$58,1/3) -> 0 | I7: =_xlfn.PERCENTILE.INC(data_CLEAN!P$3:P$58,1/3) -> 79.118478 | J7: =_xlfn.PERCENTILE.INC(data_CLEAN!R$3:R$58,1/3) -> 1.0172212 | K7: =_xlfn.PERCENTILE.INC(data_CLEAN!V$3:V$58,1/3) -> 227.21667 | L7: =_xlfn.PERCENTILE.INC(data_CLEAN!W$3:W$58,1/3) -> 2.2333333 | M7: =_xlfn.PERCENTILE.INC(data_CLEAN!X$3:X$58,1/3) -> 3 | N7: 2
A8: 66%tile | B8: =_xlfn.PERCENTILE.INC(data_CLEAN!$C$3:$C$58,2/3) -> 0.089602487 | C8: =_xlfn.PERCENTILE.INC(data_CLEAN!D$3:D$58,2/3) -> 0.096673356 | D8: =_xlfn.PERCENTILE.INC(data_CLEAN!E$3:E$58,2/3) -> 1.4680733 | E8: =_xlfn.PERCENTILE.INC(data_CLEAN!F$3:F$58,2/3) -> 581.41732 | F8: =_xlfn.PERCENTILE.INC(data_CLEAN!G$3:G$58,2/3) -> 249.73568 | G8: =_xlfn.PERCENTILE.INC(data_CLEAN!M$3:M$58,2/3) -> 27337.969 | H8: =_xlfn.PERCENTILE.INC(data_CLEAN!N$3:N$58,2/3) -> 1.9431145 | I8: =_xlfn.PERCENTILE.INC(data_CLEAN!P$3:P$58,2/3) -> 96.400499 | J8: =_xlfn.PERCENTILE.INC(data_CLEAN!R$3:R$58,2/3) -> 1.203867 | K8: =_xlfn.PERCENTILE.INC(data_CLEAN!V$3:V$58,2/3) -> 381.98333 | L8: =_xlfn.PERCENTILE.INC(data_CLEAN!W$3:W$58,2/3) -> 5.0333333 | M8: =_xlfn.PERCENTILE.INC(data_CLEAN!X$3:X$58,2/3) -> 5.6666667 | N8: 3
A12: Qualitative metric, low is good and high is bad | B12: PV_Inefficiency_22 Need | C12: Trk_Inefficiency_22 Need | D12: PV_Inefficiency_50 Need | E12: Trk_Inefficiency_50 Need | F12: Equity
A13: Low | B13: 1 | C13: 1 | D13: 1 | E13: 1 | F13: 1
A14: Med | B14: 2 | C14: 2 | D14: 2 | E14: 2 | F14: 2
A15: High | B15: 3 | C15: 3 | D15: 3 | E15: 3 | F15: 3
A18: Qualitative metric, low is bad, high is good | B18: Multimodal Need
A19: Low | B19: 3
A20: Med | B20: 2
A21: High | B21: 1
A24: Binary metric, Need score dependent on the nature of the metric | B24: frontage roads exists? | C24: frontage roads Need | D24: 16' bridge or lower | E24: 16' bridge or lower Need
A25: 1 | B25: Yes | C25: 0 | D25: Yes | E25: 1
A26: 0 | B26: No | C26: 1 | D26: No | E26: 0
A29: The higher the value, the lower the need | B29: shoulder width | C29: shoulder width Need | D29: Bridge Condition | E29: Bridge Condition Need
B30: less than below | C30: 3 | D30: less than below | E30: 3
A31: 33%tile | B31: =_xlfn.PERCENTILE.INC(data_CLEAN!Q$3:Q$58,1/3) -> 6.0952787 | C31: 2 | D31: =_xlfn.PERCENTILE.INC(data_CLEAN!S$3:S$58,1/3) -> 1.0139215 | E31: 2
A32: 66%tile | B32: =_xlfn.PERCENTILE.INC(data_CLEAN!Q$3:Q$58,2/3) -> 7.704762 | C32: 1 | D32: =_xlfn.PERCENTILE.INC(data_CLEAN!S$3:S$58,2/3) -> 1.0463582 | E32: 1
A36: Special metric | B36: ITS Need
A37: equals to 1 | B37: 1
A38: greater than 1 | B38: 0
A42: Bucket weight lookup - change "Bucket Weight" values to change the weight of each bucket in the final score
A43: Unique Bucket | B43: Bucket sum | C43: Bucket Weight
A44: {=_xlfn.UNIQUE(B53:B75)} -> mobility, reliability, and connectvity | B44: =SUMIF($B$53:$B$75,A44,$C$53:$C$75) -> 10 | C44: 0.25
A45: safety and security | B45: =SUMIF($B$53:$B$75,A45,$C$53:$C$75) -> 2 | C45: 0.25
A46: asset preservation and technology deployment | B46: =SUMIF($B$53:$B$75,A46,$C$53:$C$75) -> 7 | C46: 0.25
A47: customer service, stewardship and sustainability, and equity | B47: =SUMIF($B$53:$B$75,A47,$C$53:$C$75) -> 4 | C47: 0.25
A50: Weighting Crosswalk
A52: Metric | B52: Bucket | C52: uno | D52: Bucket sum | E52: Metric Weight within the bucket | F52: Bucket Weight within the final score | G52: Metric Score | H52: Final Score
A53: existing vc | B53: mobility, reliability, and connectvity | C53: 1 | D53: =VLOOKUP(B53,$A$44:$B$47,2,FALSE) -> 10 | E53: =C53/D53 -> 0.1 | F53: =VLOOKUP(B53,$A$44:$C$47,3,FALSE) -> 0.25 | G53: look up metric above for score, use highlighted cells | H53: determined by: SUM(metric weight X bucket weight X Metric Score) for each metric
A54: forecasted vc | B54: mobility, reliability, and connectvity | C54: 1 | D54: =VLOOKUP(B54,$A$44:$B$47,2,FALSE) -> 10 | E54: =C54/D54 -> 0.1 | F54: =VLOOKUP(B54,$A$44:$C$47,3,FALSE) -> 0.25
A55: TTRI | B55: mobility, reliability, and connectvity | C55: 1 | D55: =VLOOKUP(B55,$A$44:$B$47,2,FALSE) -> 10 | E55: =C55/D55 -> 0.1 | F55: =VLOOKUP(B55,$A$44:$C$47,3,FALSE) -> 0.25
A56: delay_psgr_s_corr | B56: mobility, reliability, and connectvity | C56: 1 | D56: =VLOOKUP(B56,$A$44:$B$47,2,FALSE) -> 10 | E56: =C56/D56 -> 0.1 | F56: =VLOOKUP(B56,$A$44:$C$47,3,FALSE) -> 0.25
A57: delay_trk_s_corr | B57: mobility, reliability, and connectvity | C57: 1 | D57: =VLOOKUP(B57,$A$44:$B$47,2,FALSE) -> 10 | E57: =C57/D57 -> 0.1 | F57: =VLOOKUP(B57,$A$44:$C$47,3,FALSE) -> 0.25
A58: PV_Inefficiency_22 | B58: mobility, reliability, and connectvity | C58: 1 | D58: =VLOOKUP(B58,$A$44:$B$47,2,FALSE) -> 10 | E58: =C58/D58 -> 0.1 | F58: =VLOOKUP(B58,$A$44:$C$47,3,FALSE) -> 0.25
A59: Trk_Inefficiency_22 | B59: mobility, reliability, and connectvity | C59: 1 | D59: =VLOOKUP(B59,$A$44:$B$47,2,FALSE) -> 10 | E59: =C59/D59 -> 0.1 | F59: =VLOOKUP(B59,$A$44:$C$47,3,FALSE) -> 0.25
A60: PV_Inefficiency_50 | B60: mobility, reliability, and connectvity | C60: 1 | D60: =VLOOKUP(B60,$A$44:$B$47,2,FALSE) -> 10 | E60: =C60/D60 -> 0.1 | F60: =VLOOKUP(B60,$A$44:$C$47,3,FALSE) -> 0.25
A61: Trk_Inefficiency_50 | B61: mobility, reliability, and connectvity | C61: 1 | D61: =VLOOKUP(B61,$A$44:$B$47,2,FALSE) -> 10 | E61: =C61/D61 -> 0.1 | F61: =VLOOKUP(B61,$A$44:$C$47,3,FALSE) -> 0.25
A62: Multimodal | B62: mobility, reliability, and connectvity | C62: 1 | D62: =VLOOKUP(B62,$A$44:$B$47,2,FALSE) -> 10 | E62: =C62/D62 -> 0.1 | F62: =VLOOKUP(B62,$A$44:$C$47,3,FALSE) -> 0.25
A63: Safety | B63: safety and security | C63: 1 | D63: =VLOOKUP(B63,$A$44:$B$47,2,FALSE) -> 2 | E63: =C63/D63 -> 0.5 | F63: =VLOOKUP(B63,$A$44:$C$47,3,FALSE) -> 0.25
A64: RR_crash | B64: safety and security | C64: 1 | D64: =VLOOKUP(B64,$A$44:$B$47,2,FALSE) -> 2 | E64: =C64/D64 -> 0.5 | F64: =VLOOKUP(B64,$A$44:$C$47,3,FALSE) -> 0.25
A65: frontage roads | B65: asset preservation and technology deployment | C65: 1 | D65: =VLOOKUP(B65,$A$44:$B$47,2,FALSE) -> 7 | E65: =C65/D65 -> 0.14285714 | F65: =VLOOKUP(B65,$A$44:$C$47,3,FALSE) -> 0.25
... A75: Equity | B75: customer service, stewardship and sustainability, and equity | C75: 1 | D75: =VLOOKUP(B75,$A$44:$B$47,2,FALSE) -> 4 | E75: =C75/D75 -> 0.25 | F75: =VLOOKUP(B75,$A$44:$C$47,3,FALSE) -> 0.25
A81: Criterion | B81: Goal | C81: # of Criteria within each Goal | D81: Criterion Weight within the Goal | E81: Goal Weight within the Final Score | F81: Criterion Score
A82: Existing V/C | B82: mobility, reliability, and connectvity | C82: 10 | D82: 0.1 | E82: 0.25 | F82: 1 to 3 based on tertiles
A83: Forecasted V/C | B83: mobility, reliability, and connectvity | C83: 10 | D83: 0.1 | E83: 0.25 | F83: 1 to 3 based on tertiles
A84: TTRI | B84: mobility, reliability, and connectvity | C84: 10 | D84: 0.1 | E84: 0.25 | F84: 1 to 3 based on tertiles
A85: Passenger Vehicle Delay | B85: mobility, reliability, and connectvity | C85: 10 | D85: 0.1 | E85: 0.25 | F85: 1 to 3 based on tertiles
A86: Truck Delay | B86: mobility, reliability, and connectvity | C86: 10 | D86: 0.1 | E86: 0.25 | F86: 1 to 3 based on tertiles
A87: Passenger Vehicle Route Directness 2022 | B87: mobility, reliability, and connectvity | C87: 10 | D87: 0.1 | E87: 0.25 | F87: 1 to 3 based on low/med/high
A88: Truck Route Directness 2022 | B88: mobility, reliability, and connectvity | C88: 10 | D88: 0.1 | E88: 0.25 | F88: 1 to 3 based on low/med/high
A89: Passenger Vehicle Route Directness 2050 | B89: mobility, reliability, and connectvity | C89: 10 | D89: 0.1 | E89: 0.25 | F89: 1 to 3 based on low/med/high
A90: Truck Route Directness 2050 | B90: mobility, reliability, and connectvity | C90: 10 | D90: 0.1 | E90: 0.25 | F90: 1 to 3 based on low/med/high
A91: Multimodal | B91: mobility, reliability, and connectvity | C91: 10 | D91: 0.1 | E91: 0.25 | F91: 3 to 1 based on low/med/high
A92: Safety | B92: safety and security | C92: 2 | D92: 0.5 | E92: 0.25 | F92: 1 to 3 based on tertiles
A93: Railroad Crash | B93: safety and security | C93: 2 | D93: 0.5 | E93: 0.25 | F93: 1 to 3 based on tertiles
... A104: Equity | B104: customer service, stewardship and sustainability, and equity | C104: 4 | D104: 0.25 | E104: 0.25 | F104: 1 to 3 based on low/med/high
A109: Percentiles for Network Designation Scores | B109: 0.33 | C109: 0.66
A110: People and Goods Movement | B110: =_xlfn.PERCENTILE.INC(data_MAPPING!J2:J54,1/3) -> 4.3079951 | C110: =_xlfn.PERCENTILE.INC(data_MAPPING!J2:J54,2/3) -> 5.0624681
A111: Market Access | B111: =_xlfn.PERCENTILE.INC(data_MAPPING!I2:I54,1/3) -> 3.8430229 | C111: =_xlfn.PERCENTILE.INC(data_MAPPING!I2:I54,2/3) -> 5.1781774
A112: Network Designation Score | B112: =_xlfn.PERCENTILE.INC(data_MAPPING!K2:K54,1/3) -> 8.3729031 | C112: =_xlfn.PERCENTILE.INC(data_MAPPING!K2:K54,2/3) -> 10.212962
A115: Percentiles for Needs Assessment Score | B115: 0.33 | C115: 0.66
A116: final_score | B116: =_xlfn.PERCENTILE.INC(data_MAPPING!G2:G57,1/3) -> 1.6363095 | C116: =_xlfn.PERCENTILE.INC(data_MAPPING!G2:G57,2/3) -> 1.8684524

Sheet corridor_miles
A1: corridor_j | B1: Miles
A3: 240AA1005 | B3: 12.562325
A4: FM0305-KG | B4: 19.554896
A5: FM0490-KG | B5: 13.986049
A6: FM0624-KG | B6: 97.643794
A7: FM0649-KG | B7: 76.826502
A8: FM0650-KG | B8: 3.4067871
A9: FM0681-KG | B9: 27.275757
A10: FM0755-KG | B10: 60.320466
A11: FM1015-KG | B11: 20.004862
A12: FM1017-KG | B12: 76.142924
A13: FM1021-KG | B13: 41.656805
A14: FM1023-KG | B14: 18.352813
... A58: US0385-KG | B58: 97.141263

Sheet MultimodalConnectivity_Corridor
A1: RIA_RTE_ID | B1: SUM_Miles | C1: MAX_Region | D1: Shape_Leng | E1: Corridor_j | F1: Corridor | G1: Miles | H1: Row_Labels | I1: AvgMM_Scor | J1: ObjectID | K1: Score
A2: 240AA1005 | B2: 12.562325 | C2: South | D2: 22824.638 | E2: 240AA1005 | F2: 240AA1005 | G2: 12.562325 | H2: 240AA1005 | I2: 0 | J2: 1 | K2: Low
A3: FM0305-KG | B3: 19.554896 | C3: West | D3: 36811.213 | E3: FM0305-KG | F3: FM 305 | G3: 19.554896 | H3: FM0305-KG | I3: 0 | J3: 2 | K3: Low
A4: FM0490-KG | B4: 13.986049 | C4: South | D4: 25132.156 | E4: FM0490-KG | F4: FM 490 | G4: 13.986049 | H4: FM0490-KG | I4: 0 | J4: 3 | K4: Low
A5: FM0624-KG | B5: 97.643794 | C5: South | D5: 178324.05 | E5: FM0624-KG | F5: FM 624 | G5: 97.643794 | H5: FM0624-KG | I5: 0 | J5: 4 | K5: Low
A6: FM0649-KG | B6: 76.826502 | C6: South | D6: 139249.39 | E6: FM0649-KG | F6: FM 649 | G6: 76.826502 | H6: FM0649-KG | I6: 0 | J6: 5 | K6: Low
A7: FM0650-KG | B7: 3.4067871 | C7: South | D7: 6120.7446 | E7: FM0650-KG | F7: FM 650 | G7: 3.4067871 | H7: FM0650-KG | I7: 0 | J7: 6 | K7: Low
A8: FM0681-KG | B8: 27.275757 | C8: South | D8: 49219.803 | E8: FM0681-KG | F8: FM 681 | G8: 27.275757 | H8: FM0681-KG | I8: 0 | J8: 7 | K8: Low
A9: FM0755-KG | B9: 60.320466 | C9: South | D9: 108856.44 | E9: FM0755-KG | F9: FM 755 | G9: 60.320466 | H9: FM0755-KG | I9: 0.0018938832 | J9: 8 | K9: Med
A10: FM1015-KG | B10: 20.004862 | C10: South | D10: 36081.562 | E10: FM1015-KG | F10: FM 1015 | G10: 20.004862 | H10: FM1015-KG | I10: 0 | J10: 9 | K10: Low
A11: FM1017-KG | B11: 76.142924 | C11: South | D11: 137688.42 | E11: FM1017-KG | F11: FM 1017 | G11: 76.142924 | H11: FM1017-KG | I11: 0.00080987094 | J11: 10 | K11: Med
A12: FM1021-KG | B12: 41.656805 | C12: Central | D12: 76436.193 | E12: FM1021-KG | F12: FM 1021 | G12: 41.656805 | H12: FM1021-KG | I12: 0 | J12: 11 | K12: Low
A13: FM1023-KG | B13: 18.352813 | C13: Central | D13: 33860.548 | E13: FM1023-KG | F13: FM 1023 | G13: 18.352813 | H13: FM1023-KG | I13: 0.35574849 | J13: 12 | K13: High
... A57: US0385-KG | B57: 97.141263 | C57: West | D57: 182682.61 | E57: US0385-KG | F57: US 385 | G57: 97.141263 | H57: US0385-KG | I57: 0.0030464514 | J57: 56 | K57: Med

Sheet data with previous weighted avg
C1: mobility, reliability, and connectvity | P1: safety and security - Ardurra | T1: asset preservation and technology deployment | AA1: economic competitiveness, cross-border resiliency, and sustainable funding - these measures are either addressed in equity (for econ comp) or not measurable, ignore | AB1: customer service, stewardship and sustainability, and equity
A2: corridor_j | B2: Miles | C2: existing vc | D2: forecasted vc | E2: Congestion_metric | F2: forecasted LOS | G2: TTRI | H2: delay_psgr_s_corr | I2: delay_trk_s_corr | J2: fast avoid existing | K2: fast_avoid_existing | L2: fast avoid forecasted | M2: short avoid existing | N2: short avoid forecast | O2: Multimodal | P2: Safety | Q2: truck-related crashes | R2: bridge strikes - Not Important bc addressed in 15 ft or lower metric | S2: RR_crash | T2: frontage roads | U2: % lane mileage with 2 or less lanes | V2: shoulder width | W2: Pavement Conditions | X2: Bridge Condition | Y2: 16' bridge or lower | Z2: ITS-Ardurra | AA2: exposure to risk | AB2: access to historic, cultural, and tourist activities | AC2: EV charging inventory and proximity | AD2: access to rest areas/truck parking | AE2: R2R_N_corridors_Final_Equity_091124
A3: 240AA1005 | B3: 12.562325 | C3: 0 | D3: 0 | E3: 3.464614 | G3: 0 | H3: 0 | I3: 0 | J3: -2.977551 | L3: Medium | M3: 362.12547 | N3: Medium | O3: 0 | P3: =VLOOKUP(A3,[2]METRICS!$AA$2:$AC$70,3,FALSE) -> 0 | R3: 0 | S3: =VLOOKUP(A3,[2]METRICS!$AA$2:$AD$70,4,FALSE) -> 0 | T3: 0 | U3: 100 | V3: 0 | W3: 3.464614 | X3: 8.828586 | Y3: 0 | Z3: 3.464614 | AB3: 209 | AC3: 1.4 | AD3: 2 | AE3: Low
A4: FM0305-KG | B4: 19.554896 | C4: 0.050006 | D4: 0.065091 | E4: 0.601931 | G4: 0 | H4: 0 | I4: 0 | J4: 1777.7505 | L4: High | M4: -619.10374 | N4: High | O4: 0 | P4: =VLOOKUP(A4,[2]METRICS!$AA$2:$AC$70,3,FALSE) -> 8479.4644 | R4: 0 | S4: =VLOOKUP(A4,[2]METRICS!$AA$2:$AD$70,4,FALSE) -> 0 | T4: 0 | U4: 89.065645 | V4: 6.605263 | W4: 0.665235 | X4: 0.602459 | Y4: 0 | Z4: 0.631985 | AB4: 101.45 | AC4: 0.2 | AD4: 2 | AE4: Medium
A5: FM0490-KG | B5: 13.986049 | C5: 0.06405 | D5: 0.09544 | E5: 1.561637 | G5: 0 | H5: 0 | I5: 0 | J5: -42.687115 | L5: Low | M5: -65.134493 | N5: Low | O5: 0 | P5: =VLOOKUP(A5,[2]METRICS!$AA$2:$AC$70,3,FALSE) -> 8375.8624 | R5: 0 | S5: =VLOOKUP(A5,[2]METRICS!$AA$2:$AD$70,4,FALSE) -> 0.010102 | T5: 0 | U5: 100 | V5: 3 | W5: 1.683598 | X5: 1.562647 | Y5: 0 | Z5: 1.561637 | AB5: 516.1 | AC5: 5.9 | AD5: 3 | AE5: Low
A6: FM0624-KG | B6: 97.643794 | C6: 0.031003 | D6: 0.028794 | E6: 0.75894 | G6: 0 | H6: 0 | I6: 0 | J6: 1089.4293 | L6: Medium | M6: -155.06407 | N6: Medium | O6: 0 | P6: =VLOOKUP(A6,[2]METRICS!$AA$2:$AC$70,3,FALSE) -> 8709.6248 | R6: 1 | S6: =VLOOKUP(A6,[2]METRICS!$AA$2:$AD$70,4,FALSE) -> 0 | T6: 0 | U6: 99.089982 | V6: 2.917808 | W6: 1.444715 | X6: 0.775994 | Y6: 0 | Z6: 0.75894 | AB6: 356.9 | AC6: 1.3 | AD6: 9 | AE6: Medium
A7: FM0649-KG | B7: 76.826502 | C7: 0.025319 | D7: 0.025827 | E7: 1.218667 | G7: 0 | H7: 0 | I7: 0 | J7: -2.868065 | L7: Low | M7: 98.831997 | N7: Low | O7: 0 | P7: =VLOOKUP(A7,[2]METRICS!$AA$2:$AC$70,3,FALSE) -> 11762.504 | R7: 0 | S7: =VLOOKUP(A7,[2]METRICS!$AA$2:$AD$70,4,FALSE) -> 6.909667 | T7: 0 | U7: 100 | V7: 2.309859 | W7: 1.386415 | X7: 1.245034 | Y7: 0 | Z7: 1.218667 | AB7: 419.65 | AC7: 2.1 | AD7: 2 | AE7: Medium
A8: FM0650-KG | B8: 3.4067871 | C8: 0 | D8: 0 | E8: 0.760649 | G8: 0 | H8: 0 | I8: 0 | J8: 0.203797 | L8: Medium | M8: 0.255257 | N8: Medium | O8: 0 | P8: =VLOOKUP(A8,[2]METRICS!$AA$2:$AC$70,3,FALSE) -> 30777.864 | R8: 0 | S8: =VLOOKUP(A8,[2]METRICS!$AA$2:$AD$70,4,FALSE) -> 0 | T8: 0 | U8: 100 | V8: 7.6 | W8: 0.760649 | X8: 0.772023 | Y8: 0 | Z8: 0.760649 | AB8: 223.45 | AC8: 0.8 | AD8: 0 | AE8: Medium
A9: FM0681-KG | B9: 27.275757 | C9: 0.072927 | D9: 0.087304 | E9: 1.13273 | G9: 0 | H9: 0 | I9: 0 | J9: -178.48682 | L9: Medium | M9: -112.43302 | N9: Medium | O9: 0 | P9: =VLOOKUP(A9,[2]METRICS!$AA$2:$AC$70,3,FALSE) -> 629666.78 | R9: 0 | S9: =VLOOKUP(A9,[2]METRICS!$AA$2:$AD$70,4,FALSE) -> 0 | T9: 0 | U9: 99.978006 | V9: 6.925926 | W9: 1.13273 | X9: 1.13273 | Y9: 0 | Z9: 1.13273 | AB9: 525.1 | AC9: 5.2 | AD9: 3 | AE9: Low
A10: FM0755-KG | B10: 60.320466 | C10: 0.072657 | D10: 0.085255 | E10: 1.146443 | G10: 0 | H10: 0 | I10: 0 | J10: -27.727687 | L10: Low | M10: -35.845732 | N10: Low | O10: 0.001894 | P10: =VLOOKUP(A10,[2]METRICS!$AA$2:$AC$70,3,FALSE) -> 17975.935 | R10: 0 | S10: =VLOOKUP(A10,[2]METRICS!$AA$2:$AD$70,4,FALSE) -> 0 | T10: 0 | U10: 92.70038 | V10: 7.084746 | W10: 2.273558 | X10: 1.151112 | Y10: 0 | Z10: 1.146443 | AB10: 447.4 | AC10: 3.1 | AD10: 3 | AE10: High
A11: FM1015-KG | B11: 20.004862 | C11: 0.015568 | D11: 0.023261 | E11: 0.320286 | G11: 0 | H11: 0 | I11: 0 | J11: -18.00541 | L11: Medium | M11: 40.227235 | N11: Medium | O11: 0 | P11: =VLOOKUP(A11,[2]METRICS!$AA$2:$AC$70,3,FALSE) -> 522528.69 | R11: 0 | S11: =VLOOKUP(A11,[2]METRICS!$AA$2:$AD$70,4,FALSE) -> 0 | T11: 0 | U11: 84.658698 | V11: 7.6 | W11: 0.394136 | X11: 0.322772 | Y11: 0 | Z11: 0.320286 | AB11: 575.05 | AC11: 8.6 | AD11: 3 | AE11: Low
A12: FM1017-KG | B12: 76.142924 | C12: 0.007939 | D12: 0.008919 | E12: 2.312309 | G12: 0 | H12: 0 | I12: 0 | J12: -533.49196 | L12: Medium | M12: 155.04097 | N12: Medium | O12: 0.00081 | P12: =VLOOKUP(A12,[2]METRICS!$AA$2:$AC$70,3,FALSE) -> 27659.271 | R12: 0 | S12: =VLOOKUP(A12,[2]METRICS!$AA$2:$AD$70,4,FALSE) -> 0 | T12: 0 | U12: 100 | V12: 8.486486 | W12: 3.538065 | X12: 2.312309 | Y12: 0 | Z12: 2.312309 | AB12: 535.7 | AC12: 3.7 | AD12: 4 | AE12: Medium
A13: FM1021-KG | B13: 41.656805 | C13: 0.107993 | D13: 0.124902 | E13: 1.249874 | G13: 0 | H13: 0 | I13: 0 | J13: 69.662146 | L13: Medium | M13: 2094.9243 | N13: Medium | O13: 0 | P13: =VLOOKUP(A13,[2]METRICS!$AA$2:$AC$70,3,FALSE) -> 64.758974 | R13: 0 | S13: =VLOOKUP(A13,[2]METRICS!$AA$2:$AD$70,4,FALSE) -> 0 | T13: 0 | U13: 87.052459 | V13: 5.238095 | W13: 2.095135 | X13: 1.703813 | Y13: 0 | Z13: 1.249874 | AB13: 122.5 | AC13: 3.2 | AD13: 3 | AE13: Medium
A14: FM1023-KG | B14: 18.352813 | C14: 0.02113 | D14: 0.020559 | E14: 0.439314 | G14: 0 | H14: 43318.667 | I14: 0 | J14: 1.521053 | L14: Medium | M14: 2598.102 | N14: Medium | O14: 0.355748 | P14: =VLOOKUP(A14,[2]METRICS!$AA$2:$AC$70,3,FALSE) -> 1010.1164 | R14: 0 | S14: =VLOOKUP(A14,[2]METRICS!$AA$2:$AD$70,4,FALSE) -> 0 | T14: 0 | U14: 86.868532 | V14: 3 | W14: 0.439314 | X14: 0.439314 | Y14: 0 | Z14: 0.439314 | AB14: 331.65 | AC14: 4.1 | AD14: 5 | AE14: High
... A58: US0385-KG | B58: 97.141263 | C58: 0.057407 | D58: 0.069119 | E58: 0.751745 | G58: 2.125449 | H58: 2391.8473 | I58: 1210.895 | J58: 742.34005 | L58: High | M58: -45.359435 | N58: High | O58: 0.003046 | P58: =VLOOKUP(A58,[2]METRICS!$AA$2:$AC$70,3,FALSE) -> 9416.6644 | R58: 1 | S58: =VLOOKUP(A58,[2]METRICS!$AA$2:$AD$70,4,FALSE) -> 2.611485 | T58: 0 | U58: 62.757091 | V58: 9.284768 | W58: 0.80999 | X58: 0.753506 | Y58: 0 | Z58: 0.751745 | AB58: 178.25 | AC58: 2.3 | AD58: 4 | AE58: Medium
